{
  "type": "Feature",
  "properties": {
    "gn:admin1_code":"6.0",
    "gn:asciiname":"Majatshippo",
    "gn:country_code":"BW",
    "gn:dem":1027,
    "gn:feature_class":"P",
    "gn:feature_code":"PPLL",
    "gn:name":"Majatshippo",
    "gn:population":0,
    "gn:timezone":"Africa/Gaborone",
    "iso:country":"BW",
    "wof:name":"Majatshippo",
    "wof:placetype":"locality"
},
  "geometry": {"coordinates":[25.91262,-24.04981],"type":"Point"}
}