{
  "type": "Feature",
  "properties": {
    "gn:admin1_code":"0.0",
    "gn:asciiname":"Baines Drift",
    "gn:country_code":"BW",
    "gn:dem":732,
    "gn:feature_class":"P",
    "gn:feature_code":"PPL",
    "gn:name":"Baines Drift",
    "gn:population":0,
    "gn:timezone":"Africa/Gaborone",
    "iso:country":"BW",
    "wof:name":"Baines Drift",
    "wof:placetype":"locality"
},
  "geometry": {"coordinates":[28.75,-22.48333],"type":"Point"}
}