{
  "type": "Feature",
  "properties": {
    "gn:admin1_code":"5.0",
    "gn:asciiname":"Mmanfoditshe",
    "gn:country_code":"BW",
    "gn:dem":975,
    "gn:feature_class":"P",
    "gn:feature_code":"PPLL",
    "gn:name":"Mmanfoditshe",
    "gn:population":0,
    "gn:timezone":"Africa/Gaborone",
    "iso:country":"BW",
    "wof:name":"Mmanfoditshe",
    "wof:placetype":"locality"
},
  "geometry": {"coordinates":[26.00822,-24.21644],"type":"Point"}
}