{
  "type": "Feature",
  "properties": {
    "gn:admin1_code":"1.0",
    "gn:asciiname":"Mookane",
    "gn:country_code":"BW",
    "gn:dem":957,
    "gn:feature_class":"P",
    "gn:feature_code":"PPLL",
    "gn:name":"Mookane",
    "gn:population":0,
    "gn:timezone":"Africa/Gaborone",
    "iso:country":"BW",
    "wof:name":"Mookane",
    "wof:placetype":"locality"
},
  "geometry": {"coordinates":[27.11469,-21.64969],"type":"Point"}
}