{
  "type": "Feature",
  "properties": {
    "gn:admin1_code":"0.0",
    "gn:asciiname":"Khama Khama",
    "gn:cc2":"BW",
    "gn:country_code":"BW",
    "gn:dem":934,
    "gn:feature_class":"P",
    "gn:feature_code":"PPL",
    "gn:name":"Khama Khama",
    "gn:population":0,
    "gn:timezone":"Africa/Gaborone",
    "iso:country":"BW",
    "name:und_x_variant":[
        "Khama",
        "Khama Khama"
    ],
    "wof:name":"Khama Khama",
    "wof:placetype":"locality"
},
  "geometry": {"coordinates":[24.98333,-20.05],"type":"Point"}
}