{
  "type": "Feature",
  "properties": {
    "gn:admin1_code":"10.0",
    "gn:asciiname":"Papa ya Morotsi",
    "gn:country_code":"BW",
    "gn:dem":1266,
    "gn:feature_class":"P",
    "gn:feature_code":"PPLL",
    "gn:name":"Papa ya Morotsi",
    "gn:population":0,
    "gn:timezone":"Africa/Gaborone",
    "iso:country":"BW",
    "wof:name":"Papa ya Morotsi",
    "wof:placetype":"locality"
},
  "geometry": {"coordinates":[25.29332,-25.38313],"type":"Point"}
}