{
  "type": "Feature",
  "properties": {
    "gn:admin1_code":"6.0",
    "gn:asciiname":"Ramotlhabeng",
    "gn:country_code":"BW",
    "gn:dem":1120,
    "gn:feature_class":"P",
    "gn:feature_code":"PPLL",
    "gn:name":"Ramotlhabeng",
    "gn:population":0,
    "gn:timezone":"Africa/Gaborone",
    "iso:country":"BW",
    "wof:name":"Ramotlhabeng",
    "wof:placetype":"locality"
},
  "geometry": {"coordinates":[25.62227,-24.73153],"type":"Point"}
}