{
  "type": "Feature",
  "properties": {
    "gn:admin1_code":"3.0",
    "gn:asciiname":"Barachu",
    "gn:country_code":"BW",
    "gn:dem":1185,
    "gn:feature_class":"P",
    "gn:feature_code":"PPL",
    "gn:name":"Barachu",
    "gn:population":0,
    "gn:timezone":"Africa/Gaborone",
    "iso:country":"BW",
    "wof:name":"Barachu",
    "wof:placetype":"locality"
},
  "geometry": {"coordinates":[21.81667,-23.01667],"type":"Point"}
}