{
  "type": "Feature",
  "properties": {
    "gn:admin1_code":"10.0",
    "gn:asciiname":"Lotlhakane",
    "gn:country_code":"BW",
    "gn:dem":1171,
    "gn:feature_class":"P",
    "gn:feature_code":"PPLL",
    "gn:name":"Lotlhakane",
    "gn:population":0,
    "gn:timezone":"Africa/Gaborone",
    "iso:country":"BW",
    "name:fra_x_preferred":[
        "Lotlhakane"
    ],
    "name:ita_x_preferred":[
        "Lotlhakane"
    ],
    "name:mlg_x_preferred":[
        "Lotlhakane"
    ],
    "name:nld_x_preferred":[
        "Lotlhakane"
    ],
    "name:pol_x_preferred":[
        "Lotlhakane"
    ],
    "name:spa_x_preferred":[
        "Lotlhakane"
    ],
    "name:swa_x_preferred":[
        "Lotlhakane"
    ],
    "name:swe_x_preferred":[
        "Lotlhakane"
    ],
    "wof:name":"Lotlhakane",
    "wof:placetype":"locality"
},
  "geometry": {"coordinates":[25.48187,-25.07976],"type":"Point"}
}