{
  "type": "Feature",
  "properties": {
    "gn:admin1_code":"1.0",
    "gn:asciiname":"Letshana",
    "gn:country_code":"BW",
    "gn:dem":1019,
    "gn:feature_class":"P",
    "gn:feature_code":"PPLL",
    "gn:name":"Letshana",
    "gn:population":0,
    "gn:timezone":"Africa/Gaborone",
    "iso:country":"BW",
    "wof:name":"Letshana",
    "wof:placetype":"locality"
},
  "geometry": {"coordinates":[27.01128,-21.92599],"type":"Point"}
}