{
  "type": "Feature",
  "properties": {
    "gn:admin1_code":"9.0",
    "gn:asciiname":"Kika",
    "gn:country_code":"BW",
    "gn:dem":1079,
    "gn:feature_class":"P",
    "gn:feature_code":"PPLL",
    "gn:name":"Kika",
    "gn:population":0,
    "gn:timezone":"Africa/Gaborone",
    "iso:country":"BW",
    "name:ceb_x_preferred":[
        "Kika"
    ],
    "name:deu_x_preferred":[
        "Kika"
    ],
    "name:fas_x_preferred":[
        "\u06a9\u06cc\u06a9\u0627"
    ],
    "name:fra_x_preferred":[
        "Kika"
    ],
    "name:heb_x_preferred":[
        "\u05e7\u05d9\u05e7\u05d4"
    ],
    "name:hun_x_preferred":[
        "Kika"
    ],
    "name:ita_x_preferred":[
        "Kika"
    ],
    "name:nld_x_preferred":[
        "Kika"
    ],
    "name:por_x_preferred":[
        "Kika"
    ],
    "name:swe_x_preferred":[
        "Kika"
    ],
    "wof:name":"Kika",
    "wof:placetype":"locality"
},
  "geometry": {"coordinates":[25.7115,-24.93293],"type":"Point"}
}