{
  "type": "Feature",
  "properties": {
    "gn:admin1_code":"1.0",
    "gn:asciiname":"Tlhalerwane",
    "gn:country_code":"BW",
    "gn:dem":1020,
    "gn:feature_class":"P",
    "gn:feature_code":"PPLL",
    "gn:name":"Tlhalerwane",
    "gn:population":0,
    "gn:timezone":"Africa/Gaborone",
    "iso:country":"BW",
    "wof:name":"Tlhalerwane",
    "wof:placetype":"locality"
},
  "geometry": {"coordinates":[26.07005,-23.58144],"type":"Point"}
}