{
  "type": "Feature",
  "properties": {
    "gn:country":"BW",
    "gn:fcode":"PPL",
    "gn:pop":961,
    "iso:country":"BW",
    "name:bul_x_preferred":[
        "\u041a\u0430\u0447\u0438\u043a\u0430\u0443"
    ],
    "name:ceb_x_preferred":[
        "Kachikau"
    ],
    "name:eng_x_preferred":[
        "Kachikau"
    ],
    "name:fra_x_preferred":[
        "Kachikau"
    ],
    "name:ita_x_preferred":[
        "Kachikau"
    ],
    "name:mlg_x_preferred":[
        "Kachikau"
    ],
    "name:nld_x_preferred":[
        "Kachikau"
    ],
    "name:pol_x_preferred":[
        "Kachikau"
    ],
    "name:swa_x_preferred":[
        "Kachikau"
    ],
    "name:swe_x_preferred":[
        "Kachikau"
    ],
    "name:tsn_x_preferred":[
        "Kachikau"
    ],
    "qs:name":"Kachikau",
    "qs:photos_9r":0,
    "qs:photos_sr":0,
    "qs:pop_sr":"2",
    "wd:wordcount":90,
    "wof:name":"Kachikau",
    "wof:placetype":"locality",
    "wof:population":961
},
  "geometry": {"coordinates":[24.46667,-18.16667],"type":"Point"}
}