{
  "type": "Feature",
  "properties": {
    "gn:admin1_code":"3.0",
    "gn:asciiname":"Kukumane Kraal",
    "gn:country_code":"BW",
    "gn:dem":997,
    "gn:feature_class":"P",
    "gn:feature_code":"PPL",
    "gn:name":"Kukumane Kraal",
    "gn:population":0,
    "gn:timezone":"Africa/Gaborone",
    "iso:country":"BW",
    "wof:name":"Kukumane Kraal",
    "wof:placetype":"locality"
},
  "geometry": {"coordinates":[24.18333,-23.01667],"type":"Point"}
}