{
  "type": "Feature",
  "properties": {
    "gn:admin1_code":"1.0",
    "gn:asciiname":"Seokane",
    "gn:country_code":"BW",
    "gn:dem":950,
    "gn:feature_class":"P",
    "gn:feature_code":"PPL",
    "gn:name":"Seokane",
    "gn:population":0,
    "gn:timezone":"Africa/Gaborone",
    "iso:country":"BW",
    "wof:name":"Seokane",
    "wof:placetype":"locality"
},
  "geometry": {"coordinates":[27.39913,-22.01704],"type":"Point"}
}