{
  "type": "Feature",
  "properties": {
    "gn:admin1_code":"1.0",
    "gn:asciiname":"Mmabogopa",
    "gn:country_code":"BW",
    "gn:dem":1062,
    "gn:feature_class":"P",
    "gn:feature_code":"PPLL",
    "gn:name":"Mmabogopa",
    "gn:population":0,
    "gn:timezone":"Africa/Gaborone",
    "iso:country":"BW",
    "wof:name":"Mmabogopa",
    "wof:placetype":"locality"
},
  "geometry": {"coordinates":[26.80722,-22.38622],"type":"Point"}
}