{
  "type": "Feature",
  "properties": {
    "gn:gn_country":"BW",
    "gn:gn_fcode":"PPL",
    "gn:gn_pop":20,
    "gn:population":20,
    "iso:country":"BW",
    "qs_pg:aaroncc":"BW",
    "qs_pg:gn_country":"BW",
    "qs_pg:gn_fcode":"PPL",
    "qs_pg:gn_pop":20,
    "qs_pg:name":"Moeng",
    "qs_pg:photos_9r":0,
    "qs_pg:photos_sr":0,
    "qs_pg:pop_sr":1,
    "qs_pg:qs_pg_placetype":"locality",
    "wof:name":"Moeng",
    "wof:placetype":"locality",
    "wof:population":20
},
  "geometry": {"coordinates":[27.61139,-22.68054],"type":"Point"}
}