{
  "type": "Feature",
  "properties": {
    "gn:admin1_code":"6.0",
    "gn:asciiname":"Tshiping",
    "gn:country_code":"BW",
    "gn:dem":1035,
    "gn:feature_class":"P",
    "gn:feature_code":"PPLL",
    "gn:name":"Tshiping",
    "gn:population":0,
    "gn:timezone":"Africa/Gaborone",
    "iso:country":"BW",
    "wof:name":"Tshiping",
    "wof:placetype":"locality"
},
  "geometry": {"coordinates":[25.6583,-24.5005],"type":"Point"}
}