{
  "type": "Feature",
  "properties": {
    "gn:admin1_code":"1.0",
    "gn:asciiname":"Rametsana",
    "gn:country_code":"BW",
    "gn:dem":982,
    "gn:feature_class":"P",
    "gn:feature_code":"PPLL",
    "gn:name":"Rametsana",
    "gn:population":0,
    "gn:timezone":"Africa/Gaborone",
    "iso:country":"BW",
    "wof:name":"Rametsana",
    "wof:placetype":"locality"
},
  "geometry": {"coordinates":[26.0522,-23.48712],"type":"Point"}
}