{
  "type": "Feature",
  "properties": {
    "gn:admin1_code":"10.0",
    "gn:asciiname":"Mokata",
    "gn:country_code":"BW",
    "gn:dem":1147,
    "gn:feature_class":"P",
    "gn:feature_code":"PPLL",
    "gn:name":"Mokata",
    "gn:population":0,
    "gn:timezone":"Africa/Gaborone",
    "iso:country":"BW",
    "wof:name":"Mokata",
    "wof:placetype":"locality"
},
  "geometry": {"coordinates":[25.62201,-24.79422000000001],"type":"Point"}
}