{
  "type": "Feature",
  "properties": {
    "gn:admin1_code":"1.0",
    "gn:asciiname":"Ditsinane",
    "gn:country_code":"BW",
    "gn:dem":1028,
    "gn:feature_class":"P",
    "gn:feature_code":"PPL",
    "gn:name":"Ditsinane",
    "gn:population":0,
    "gn:timezone":"Africa/Gaborone",
    "iso:country":"BW",
    "wof:name":"Ditsinane",
    "wof:placetype":"locality"
},
  "geometry": {"coordinates":[25.83333,-21.41667],"type":"Point"}
}