{
  "type": "Feature",
  "properties": {
    "gn:admin1_code":"0.0",
    "gn:asciiname":"Lutlhe",
    "gn:country_code":"BW",
    "gn:dem":1109,
    "gn:feature_class":"P",
    "gn:feature_code":"PPL",
    "gn:name":"Lutlhe",
    "gn:population":0,
    "gn:timezone":"Africa/Gaborone",
    "iso:country":"BW",
    "wof:name":"Lutlhe",
    "wof:placetype":"locality"
},
  "geometry": {"coordinates":[23.81667,-23.96667],"type":"Point"}
}