{
  "type": "Feature",
  "properties": {
    "gn:admin1_code":"5.0",
    "gn:asciiname":"Lokala Drift",
    "gn:country_code":"BW",
    "gn:dem":881,
    "gn:feature_class":"P",
    "gn:feature_code":"PPL",
    "gn:name":"Lokala Drift",
    "gn:population":0,
    "gn:timezone":"Africa/Gaborone",
    "iso:country":"BW",
    "name:und_x_variant":[
        "Lokala",
        "Lokala Drift"
    ],
    "wof:name":"Lokala Drift",
    "wof:placetype":"locality"
},
  "geometry": {"coordinates":[26.68333,-23.98333],"type":"Point"}
}