{
  "type": "Feature",
  "properties": {
    "gn:admin1_code":"8.0",
    "gn:asciiname":"Sekgophane",
    "gn:country_code":"BW",
    "gn:dem":1120,
    "gn:feature_class":"P",
    "gn:feature_code":"PPL",
    "gn:name":"Sekgophane",
    "gn:population":0,
    "gn:timezone":"Africa/Gaborone",
    "iso:country":"BW",
    "wof:name":"Sekgophane",
    "wof:placetype":"locality"
},
  "geometry": {"coordinates":[27.59516,-20.82127],"type":"Point"}
}