{
  "type": "Feature",
  "properties": {
    "gn:admin1_code":"1.0",
    "gn:asciiname":"Mmadikgomo",
    "gn:country_code":"BW",
    "gn:dem":720,
    "gn:feature_class":"P",
    "gn:feature_code":"PPLL",
    "gn:name":"Mmadikgomo",
    "gn:population":0,
    "gn:timezone":"Africa/Gaborone",
    "iso:country":"BW",
    "wof:name":"Mmadikgomo",
    "wof:placetype":"locality"
},
  "geometry": {"coordinates":[28.45076,-22.05393],"type":"Point"}
}