{
  "type": "Feature",
  "properties": {
    "gn:admin1_code":"1.0",
    "gn:asciiname":"Masudiakgopo",
    "gn:country_code":"BW",
    "gn:dem":986,
    "gn:feature_class":"P",
    "gn:feature_code":"PPLL",
    "gn:name":"Masudiakgopo",
    "gn:population":0,
    "gn:timezone":"Africa/Gaborone",
    "iso:country":"BW",
    "wof:name":"Masudiakgopo",
    "wof:placetype":"locality"
},
  "geometry": {"coordinates":[26.88301,-22.6374],"type":"Point"}
}