{
  "type": "Feature",
  "properties": {
    "gn:admin1_code":"1.0",
    "gn:asciiname":"Ragaobodiwe",
    "gn:country_code":"BW",
    "gn:dem":770,
    "gn:feature_class":"P",
    "gn:feature_code":"PPLL",
    "gn:name":"Ragaobodiwe",
    "gn:population":0,
    "gn:timezone":"Africa/Gaborone",
    "iso:country":"BW",
    "wof:name":"Ragaobodiwe",
    "wof:placetype":"locality"
},
  "geometry": {"coordinates":[28.29688,-21.8527],"type":"Point"}
}