{
  "type": "Feature",
  "properties": {
    "gn:admin1_code":"1.0",
    "gn:asciiname":"Maope",
    "gn:country_code":"BW",
    "gn:dem":1054,
    "gn:feature_class":"P",
    "gn:feature_code":"PPL",
    "gn:name":"Maope",
    "gn:population":0,
    "gn:timezone":"Africa/Gaborone",
    "iso:country":"BW",
    "wof:name":"Maope",
    "wof:placetype":"locality"
},
  "geometry": {"coordinates":[27.24708,-22.24934],"type":"Point"}
}