{
  "type": "Feature",
  "properties": {
    "gn:admin1_code":"10.0",
    "gn:asciiname":"Mogobe wa Kgomo",
    "gn:country_code":"BW",
    "gn:dem":1260,
    "gn:feature_class":"P",
    "gn:feature_code":"PPLL",
    "gn:name":"Mogobe wa Kgomo",
    "gn:population":0,
    "gn:timezone":"Africa/Gaborone",
    "iso:country":"BW",
    "wof:name":"Mogobe wa Kgomo",
    "wof:placetype":"locality"
},
  "geometry": {"coordinates":[25.35019,-25.48372],"type":"Point"}
}