{
  "type": "Feature",
  "properties": {
    "gn:country":"BW",
    "gn:fcode":"PPLL",
    "gn:pop":718,
    "iso:country":"BW",
    "qs:name":"Mononyane",
    "qs:photos_9r":0,
    "qs:photos_sr":0,
    "qs:pop_sr":"2",
    "wof:name":"Mononyane",
    "wof:placetype":"locality",
    "wof:population":718
},
  "geometry": {"coordinates":[25.77139,-24.54194],"type":"Point"}
}