{
  "type": "Feature",
  "properties": {
    "gn:admin1_code":"1.0",
    "gn:asciiname":"Motobetsong",
    "gn:country_code":"BW",
    "gn:dem":849,
    "gn:feature_class":"P",
    "gn:feature_code":"PPLL",
    "gn:name":"Motobetsong",
    "gn:population":0,
    "gn:timezone":"Africa/Gaborone",
    "iso:country":"BW",
    "wof:name":"Motobetsong",
    "wof:placetype":"locality"
},
  "geometry": {"coordinates":[27.73047,-22.81033],"type":"Point"}
}