{
  "type": "Feature",
  "properties": {
    "gn:admin1_code":"1.0",
    "gn:asciiname":"Nsuswane",
    "gn:country_code":"BW",
    "gn:dem":1148,
    "gn:feature_class":"P",
    "gn:feature_code":"PPLL",
    "gn:name":"Nsuswane",
    "gn:population":0,
    "gn:timezone":"Africa/Gaborone",
    "iso:country":"BW",
    "wof:name":"Nsuswane",
    "wof:placetype":"locality"
},
  "geometry": {"coordinates":[27.14121,-20.4694],"type":"Point"}
}