{
  "type": "Feature",
  "properties": {
    "gn:admin1_code":"1.0",
    "gn:asciiname":"Thokolo Two",
    "gn:country_code":"BW",
    "gn:dem":1023,
    "gn:feature_class":"P",
    "gn:feature_code":"PPLL",
    "gn:name":"Thokolo Two",
    "gn:population":0,
    "gn:timezone":"Africa/Gaborone",
    "iso:country":"BW",
    "name:und_x_variant":[
        "Thokolo 2"
    ],
    "wof:name":"Thokolo Two",
    "wof:placetype":"locality"
},
  "geometry": {"coordinates":[26.86899,-23.08682],"type":"Point"}
}