{
  "type": "Feature",
  "properties": {
    "gn:admin1_code":"10.0",
    "gn:asciiname":"Sehikile",
    "gn:country_code":"BW",
    "gn:dem":1275,
    "gn:feature_class":"P",
    "gn:feature_code":"PPLL",
    "gn:name":"Sehikile",
    "gn:population":0,
    "gn:timezone":"Africa/Gaborone",
    "iso:country":"BW",
    "wof:name":"Sehikile",
    "wof:placetype":"locality"
},
  "geometry": {"coordinates":[25.32785,-25.42077],"type":"Point"}
}