{
  "type": "Feature",
  "properties": {
    "gn:admin1_code":"10.0",
    "gn:asciiname":"Gatsatsiatsola",
    "gn:country_code":"BW",
    "gn:dem":1205,
    "gn:feature_class":"P",
    "gn:feature_code":"PPLL",
    "gn:name":"Gatsatsiatsola",
    "gn:population":0,
    "gn:timezone":"Africa/Gaborone",
    "iso:country":"BW",
    "wof:name":"Gatsatsiatsola",
    "wof:placetype":"locality"
},
  "geometry": {"coordinates":[25.4354,-25.08758],"type":"Point"}
}