{
  "type": "Feature",
  "properties": {
    "gn:admin1_code":"0.0",
    "gn:asciiname":"Mabole",
    "gn:country_code":"BW",
    "gn:dem":914,
    "gn:feature_class":"P",
    "gn:feature_code":"PPL",
    "gn:name":"Mabole",
    "gn:population":0,
    "gn:timezone":"Africa/Gaborone",
    "iso:country":"BW",
    "wof:name":"Mabole",
    "wof:placetype":"locality"
},
  "geometry": {"coordinates":[26.01667,-20.18333],"type":"Point"}
}