{
  "type": "Feature",
  "properties": {
    "gn:admin1_code":"1.0",
    "gn:asciiname":"Mmamosarwana",
    "gn:country_code":"BW",
    "gn:dem":1038,
    "gn:feature_class":"P",
    "gn:feature_code":"PPLL",
    "gn:name":"Mmamosarwana",
    "gn:population":0,
    "gn:timezone":"Africa/Gaborone",
    "iso:country":"BW",
    "wof:name":"Mmamosarwana",
    "wof:placetype":"locality"
},
  "geometry": {"coordinates":[27.21989,-22.22512],"type":"Point"}
}