{
  "type": "Feature",
  "properties": {
    "iso:country":"BW",
    "name:bul_x_preferred":[
        "\u0421\u0435\u0440\u043e\u043d\u0433\u0430"
    ],
    "name:ceb_x_preferred":[
        "Seronga"
    ],
    "name:dan_x_preferred":[
        "Seronga"
    ],
    "name:ell_x_preferred":[
        "\u03a3\u03b5\u03c1\u03cc\u03bd\u03b3\u03ba\u03b1"
    ],
    "name:eng_x_preferred":[
        "Seronga"
    ],
    "name:fas_x_preferred":[
        "\u0633\u0631\u0648\u0646\u06af\u0627\u060c \u0628\u0648\u062a\u0633\u0648\u0627\u0646\u0627"
    ],
    "name:fas_x_variant":[
        "\u0633\u0631\u0648\u0646\u06af\u0627"
    ],
    "name:fin_x_preferred":[
        "Seronga"
    ],
    "name:fra_x_preferred":[
        "Seronga"
    ],
    "name:ita_x_preferred":[
        "Seronga"
    ],
    "name:jpn_x_preferred":[
        "\u30bb\u30ed\u30f3\u30ac"
    ],
    "name:mlg_x_preferred":[
        "Seronga"
    ],
    "name:nld_x_preferred":[
        "Seronga"
    ],
    "name:pol_x_preferred":[
        "Seronga"
    ],
    "name:por_x_preferred":[
        "Seronga"
    ],
    "name:rus_x_preferred":[
        "\u0421\u0435\u0440\u043e\u043d\u0433\u0430"
    ],
    "name:swa_x_preferred":[
        "Seronga"
    ],
    "name:swe_x_preferred":[
        "Seronga"
    ],
    "name:tsn_x_preferred":[
        "Seronga"
    ],
    "name:zul_x_preferred":[
        "Seronga"
    ],
    "qs:gn_country":"BW",
    "qs:gn_fcode":"PPL",
    "qs:gn_pop":0,
    "qs:name":"Seronga",
    "qs:name_adm0":"Botswana",
    "qs:name_adm1":"North-West",
    "qs:photos":19,
    "qs:photos_1k":4,
    "qs:photos_9k":1,
    "qs:photos_9r":1,
    "qs:photos_all":19,
    "qs:photos_sr":1,
    "qs:placetype":"Town",
    "qs:pop_sr":"0",
    "qs:woe_adm0":23424755,
    "wd:wordcount":80,
    "wof:name":"Seronga",
    "wof:placetype":"locality"
},
  "geometry": {"coordinates":[22.4164,-18.8129],"type":"Point"}
}