{
  "type": "Feature",
  "properties": {
    "gn:admin1_code":"1.0",
    "gn:asciiname":"Taukome",
    "gn:country_code":"BW",
    "gn:dem":1093,
    "gn:feature_class":"P",
    "gn:feature_code":"PPLL",
    "gn:name":"Taukome",
    "gn:population":0,
    "gn:timezone":"Africa/Gaborone",
    "iso:country":"BW",
    "wof:name":"Taukome",
    "wof:placetype":"locality"
},
  "geometry": {"coordinates":[26.94999,-22.25392],"type":"Point"}
}