{
  "type": "Feature",
  "properties": {
    "gn:admin1_code":"6.0",
    "gn:asciiname":"Morobane",
    "gn:country_code":"BW",
    "gn:dem":1224,
    "gn:feature_class":"P",
    "gn:feature_code":"PPLL",
    "gn:name":"Morobane",
    "gn:population":0,
    "gn:timezone":"Africa/Gaborone",
    "iso:country":"BW",
    "wof:name":"Morobane",
    "wof:placetype":"locality"
},
  "geometry": {"coordinates":[25.26168,-24.42856],"type":"Point"}
}