{
  "type": "Feature",
  "properties": {
    "gn:admin1_code":"10.0",
    "gn:asciiname":"Theledi",
    "gn:country_code":"BW",
    "gn:dem":1065,
    "gn:feature_class":"P",
    "gn:feature_code":"PPLL",
    "gn:name":"Theledi",
    "gn:population":0,
    "gn:timezone":"Africa/Gaborone",
    "iso:country":"BW",
    "wof:name":"Theledi",
    "wof:placetype":"locality"
},
  "geometry": {"coordinates":[23.77967,-24.60366],"type":"Point"}
}