{
  "type": "Feature",
  "properties": {
    "gn:admin1_code":"1.0",
    "gn:asciiname":"Malepe",
    "gn:country_code":"BW",
    "gn:dem":1064,
    "gn:feature_class":"P",
    "gn:feature_code":"PPLL",
    "gn:name":"Malepe",
    "gn:population":0,
    "gn:timezone":"Africa/Gaborone",
    "iso:country":"BW",
    "wof:name":"Malepe",
    "wof:placetype":"locality"
},
  "geometry": {"coordinates":[26.75791,-23.07988],"type":"Point"}
}