{
  "type": "Feature",
  "properties": {
    "gn:admin1_code":"1.0",
    "gn:asciiname":"Letapana",
    "gn:country_code":"BW",
    "gn:dem":1016,
    "gn:feature_class":"P",
    "gn:feature_code":"PPLL",
    "gn:name":"Letapana",
    "gn:population":0,
    "gn:timezone":"Africa/Gaborone",
    "iso:country":"BW",
    "wof:name":"Letapana",
    "wof:placetype":"locality"
},
  "geometry": {"coordinates":[26.8597,-23.10276],"type":"Point"}
}