{
  "type": "Feature",
  "properties": {
    "gn:admin1_code":"10.0",
    "gn:asciiname":"Janki",
    "gn:country_code":"BW",
    "gn:dem":1240,
    "gn:feature_class":"P",
    "gn:feature_code":"PPLL",
    "gn:name":"Janki",
    "gn:population":0,
    "gn:timezone":"Africa/Gaborone",
    "iso:country":"BW",
    "name:ceb_x_preferred":[
        "Janki"
    ],
    "name:deu_x_preferred":[
        "Janki"
    ],
    "name:fra_x_preferred":[
        "Janki"
    ],
    "name:lit_x_preferred":[
        "Jankai"
    ],
    "name:nld_x_preferred":[
        "Janki"
    ],
    "name:pol_x_preferred":[
        "Janki"
    ],
    "wof:name":"Janki",
    "wof:placetype":"locality"
},
  "geometry": {"coordinates":[25.4197,-25.18939],"type":"Point"}
}