{
  "type": "Feature",
  "properties": {
    "gn:admin1_code":"10.0",
    "gn:asciiname":"Lepapa",
    "gn:country_code":"BW",
    "gn:dem":1202,
    "gn:feature_class":"P",
    "gn:feature_code":"PPL",
    "gn:name":"Lepapa",
    "gn:population":0,
    "gn:timezone":"Africa/Gaborone",
    "iso:country":"BW",
    "wof:name":"Lepapa",
    "wof:placetype":"locality"
},
  "geometry": {"coordinates":[24.65776,-24.74582],"type":"Point"}
}