{
  "type": "Feature",
  "properties": {
    "gn:admin1_code":"1.0",
    "gn:asciiname":"Serwe",
    "gn:country_code":"BW",
    "gn:dem":1235,
    "gn:feature_class":"P",
    "gn:feature_code":"PPLL",
    "gn:name":"Serwe",
    "gn:population":0,
    "gn:timezone":"Africa/Gaborone",
    "iso:country":"BW",
    "wof:name":"Serwe",
    "wof:placetype":"locality"
},
  "geometry": {"coordinates":[26.70108,-22.23098],"type":"Point"}
}