{
  "type": "Feature",
  "properties": {
    "gn:admin1_code":"1.0",
    "gn:asciiname":"Xalagena",
    "gn:country_code":"BW",
    "gn:dem":1066,
    "gn:feature_class":"P",
    "gn:feature_code":"PPL",
    "gn:name":"Xalagena",
    "gn:population":0,
    "gn:timezone":"Africa/Gaborone",
    "iso:country":"BW",
    "wof:name":"Xalagena",
    "wof:placetype":"locality"
},
  "geometry": {"coordinates":[26.57825,-21.66821],"type":"Point"}
}