{
  "type": "Feature",
  "properties": {
    "gn:admin1_code":"5.0",
    "gn:asciiname":"Motlhorogwane",
    "gn:country_code":"BW",
    "gn:dem":911,
    "gn:feature_class":"P",
    "gn:feature_code":"PPLL",
    "gn:name":"Motlhorogwane",
    "gn:population":0,
    "gn:timezone":"Africa/Gaborone",
    "iso:country":"BW",
    "wof:name":"Motlhorogwane",
    "wof:placetype":"locality"
},
  "geometry": {"coordinates":[26.44446,-24.14187],"type":"Point"}
}