{
  "type": "Feature",
  "properties": {
    "gn:admin1_code":"9.0",
    "gn:asciiname":"Maokamatshwane",
    "gn:country_code":"BW",
    "gn:dem":1084,
    "gn:feature_class":"P",
    "gn:feature_code":"PPLL",
    "gn:name":"Maokamatshwane",
    "gn:population":0,
    "gn:timezone":"Africa/Gaborone",
    "iso:country":"BW",
    "wof:name":"Maokamatshwane",
    "wof:placetype":"locality"
},
  "geometry": {"coordinates":[25.79454,-24.94784],"type":"Point"}
}