{
  "type": "Feature",
  "properties": {
    "gn:admin1_code":"1.0",
    "gn:asciiname":"Semitwe",
    "gn:country_code":"BW",
    "gn:dem":1091,
    "gn:feature_class":"P",
    "gn:feature_code":"PPL",
    "gn:name":"Semitwe",
    "gn:population":0,
    "gn:timezone":"Africa/Gaborone",
    "iso:country":"BW",
    "name:fra_x_preferred":[
        "Semitwe"
    ],
    "name:ita_x_preferred":[
        "Semitwe"
    ],
    "name:mlg_x_preferred":[
        "Semitwe"
    ],
    "name:nld_x_preferred":[
        "Semitwe"
    ],
    "name:pol_x_preferred":[
        "Semitwe"
    ],
    "name:swa_x_preferred":[
        "Semitwe"
    ],
    "wof:name":"Semitwe",
    "wof:placetype":"locality"
},
  "geometry": {"coordinates":[27.08028,-20.94083],"type":"Point"}
}