{
  "type": "Feature",
  "properties": {
    "gn:admin1_code":"1.0",
    "gn:asciiname":"Dinokana",
    "gn:country_code":"BW",
    "gn:dem":885,
    "gn:feature_class":"P",
    "gn:feature_code":"PPL",
    "gn:name":"Dinokana",
    "gn:population":0,
    "gn:timezone":"Africa/Gaborone",
    "iso:country":"BW",
    "name:afr_x_preferred":[
        "Dinokana"
    ],
    "name:est_x_preferred":[
        "Dinokana"
    ],
    "name:nso_x_preferred":[
        "Dinokana"
    ],
    "wof:name":"Dinokana",
    "wof:placetype":"locality"
},
  "geometry": {"coordinates":[27.56667,-22.91667],"type":"Point"}
}