{
  "type": "Feature",
  "properties": {
    "gn:admin1_code":"0.0",
    "gn:asciiname":"Tsekanyani",
    "gn:country_code":"BW",
    "gn:dem":951,
    "gn:feature_class":"P",
    "gn:feature_code":"PPL",
    "gn:name":"Tsekanyani",
    "gn:population":0,
    "gn:timezone":"Africa/Gaborone",
    "iso:country":"BW",
    "wof:name":"Tsekanyani",
    "wof:placetype":"locality"
},
  "geometry": {"coordinates":[26.61667000000001,-19.88333],"type":"Point"}
}