{
  "type": "Feature",
  "properties": {
    "gn:admin1_code":"10.0",
    "gn:asciiname":"Moswelakgosi",
    "gn:country_code":"BW",
    "gn:dem":1139,
    "gn:feature_class":"P",
    "gn:feature_code":"PPLL",
    "gn:name":"Moswelakgosi",
    "gn:population":0,
    "gn:timezone":"Africa/Gaborone",
    "iso:country":"BW",
    "wof:name":"Moswelakgosi",
    "wof:placetype":"locality"
},
  "geometry": {"coordinates":[25.61757,-24.77779],"type":"Point"}
}