{
  "type": "Feature",
  "properties": {
    "gn:admin1_code":"1.0",
    "gn:asciiname":"Peloyanaga",
    "gn:country_code":"BW",
    "gn:dem":830,
    "gn:feature_class":"P",
    "gn:feature_code":"PPLL",
    "gn:name":"Peloyanaga",
    "gn:population":0,
    "gn:timezone":"Africa/Gaborone",
    "iso:country":"BW",
    "wof:name":"Peloyanaga",
    "wof:placetype":"locality"
},
  "geometry": {"coordinates":[28.17744,-22.36812],"type":"Point"}
}