{
  "type": "Feature",
  "properties": {
    "gn:admin1_code":"1.0",
    "gn:asciiname":"Mmokwe",
    "gn:country_code":"BW",
    "gn:dem":1159,
    "gn:feature_class":"P",
    "gn:feature_code":"PPL",
    "gn:name":"Mmokwe",
    "gn:population":0,
    "gn:timezone":"Africa/Gaborone",
    "iso:country":"BW",
    "wof:name":"Mmokwe",
    "wof:placetype":"locality"
},
  "geometry": {"coordinates":[26.74634,-22.32361],"type":"Point"}
}