{
  "type": "Feature",
  "properties": {
    "gn:admin1_code":"6.0",
    "gn:asciiname":"Gomasala",
    "gn:country_code":"BW",
    "gn:dem":1152,
    "gn:feature_class":"P",
    "gn:feature_code":"PPLL",
    "gn:name":"Gomasala",
    "gn:population":0,
    "gn:timezone":"Africa/Gaborone",
    "iso:country":"BW",
    "wof:name":"Gomasala",
    "wof:placetype":"locality"
},
  "geometry": {"coordinates":[25.59194,-24.25175],"type":"Point"}
}