{
  "type": "Feature",
  "properties": {
    "gn:admin1_code":"5.0",
    "gn:asciiname":"Moralana",
    "gn:country_code":"BW",
    "gn:dem":946,
    "gn:feature_class":"P",
    "gn:feature_code":"PPLL",
    "gn:name":"Moralana",
    "gn:population":0,
    "gn:timezone":"Africa/Gaborone",
    "iso:country":"BW",
    "wof:name":"Moralana",
    "wof:placetype":"locality"
},
  "geometry": {"coordinates":[26.34416,-24.39379],"type":"Point"}
}