{
  "type": "Feature",
  "properties": {
    "gn:admin1_code":"1.0",
    "gn:asciiname":"Tlhalerwana",
    "gn:country_code":"BW",
    "gn:dem":1136,
    "gn:feature_class":"P",
    "gn:feature_code":"PPLL",
    "gn:name":"Tlhalerwana",
    "gn:population":0,
    "gn:timezone":"Africa/Gaborone",
    "iso:country":"BW",
    "wof:name":"Tlhalerwana",
    "wof:placetype":"locality"
},
  "geometry": {"coordinates":[26.85389,-22.85171],"type":"Point"}
}