{
  "type": "Feature",
  "properties": {
    "gn:admin1_code":"1.0",
    "gn:asciiname":"Nkulomolo",
    "gn:country_code":"BW",
    "gn:dem":836,
    "gn:feature_class":"P",
    "gn:feature_code":"PPLL",
    "gn:name":"Nkulomolo",
    "gn:population":0,
    "gn:timezone":"Africa/Gaborone",
    "iso:country":"BW",
    "wof:name":"Nkulomolo",
    "wof:placetype":"locality"
},
  "geometry": {"coordinates":[28.35276,-21.68851],"type":"Point"}
}