{
  "type": "Feature",
  "properties": {
    "gn:admin1_code":"1.0",
    "gn:asciiname":"Mothwane",
    "gn:country_code":"BW",
    "gn:dem":734,
    "gn:feature_class":"P",
    "gn:feature_code":"PPLL",
    "gn:name":"Mothwane",
    "gn:population":0,
    "gn:timezone":"Africa/Gaborone",
    "iso:country":"BW",
    "wof:name":"Mothwane",
    "wof:placetype":"locality"
},
  "geometry": {"coordinates":[28.48716,-21.89042],"type":"Point"}
}