{
  "type": "Feature",
  "properties": {
    "gn:admin1_code":"0.0",
    "gn:asciiname":"Moremaoto",
    "gn:country_code":"BW",
    "gn:dem":950,
    "gn:feature_class":"P",
    "gn:feature_code":"PPL",
    "gn:name":"Moremaoto",
    "gn:population":0,
    "gn:timezone":"Africa/Gaborone",
    "iso:country":"BW",
    "wof:name":"Moremaoto",
    "wof:placetype":"locality"
},
  "geometry": {"coordinates":[24.23333,-20.26667],"type":"Point"}
}