{
  "type": "Feature",
  "properties": {
    "gn:admin1_code":"6.0",
    "gn:asciiname":"Sojwe",
    "gn:country_code":"BW",
    "gn:dem":1030,
    "gn:feature_class":"P",
    "gn:feature_code":"PPLL",
    "gn:name":"Sojwe",
    "gn:population":0,
    "gn:timezone":"Africa/Gaborone",
    "iso:country":"BW",
    "name:fra_x_preferred":[
        "Sojwe"
    ],
    "name:ita_x_preferred":[
        "Sojwe"
    ],
    "name:mlg_x_preferred":[
        "Sojwe"
    ],
    "name:nld_x_preferred":[
        "Sojwe"
    ],
    "name:pol_x_preferred":[
        "Sojwe"
    ],
    "name:swa_x_preferred":[
        "Sojwe"
    ],
    "name:swe_x_preferred":[
        "Sojwe"
    ],
    "wof:name":"Sojwe",
    "wof:placetype":"locality"
},
  "geometry": {"coordinates":[25.75028,-23.43848],"type":"Point"}
}