{
  "type": "Feature",
  "properties": {
    "gn:admin1_code":"1.0",
    "gn:asciiname":"Dilolwane",
    "gn:country_code":"BW",
    "gn:dem":981,
    "gn:feature_class":"P",
    "gn:feature_code":"PPLL",
    "gn:name":"Dilolwane",
    "gn:population":0,
    "gn:timezone":"Africa/Gaborone",
    "iso:country":"BW",
    "wof:name":"Dilolwane",
    "wof:placetype":"locality"
},
  "geometry": {"coordinates":[27.12652000000001,-22.25726],"type":"Point"}
}