{
  "type": "Feature",
  "properties": {
    "gn:admin1_code":"1.0",
    "gn:asciiname":"Mogaleng",
    "gn:country_code":"BW",
    "gn:dem":894,
    "gn:feature_class":"P",
    "gn:feature_code":"PPLL",
    "gn:name":"Mogaleng",
    "gn:population":0,
    "gn:timezone":"Africa/Gaborone",
    "iso:country":"BW",
    "wof:name":"Mogaleng",
    "wof:placetype":"locality"
},
  "geometry": {"coordinates":[27.57369000000001,-22.51382000000001],"type":"Point"}
}