{
  "type": "Feature",
  "properties": {
    "gn:admin1_code":"5.0",
    "gn:asciiname":"Kgomo-Dia-Tshaba",
    "gn:country_code":"BW",
    "gn:dem":1039,
    "gn:feature_class":"P",
    "gn:feature_code":"PPLL",
    "gn:name":"Kgomo-Dia-Tshaba",
    "gn:population":0,
    "gn:timezone":"Africa/Gaborone",
    "iso:country":"BW",
    "wof:name":"Kgomo-Dia-Tshaba",
    "wof:placetype":"locality"
},
  "geometry": {"coordinates":[26.10362000000001,-23.65712000000001],"type":"Point"}
}