{
  "type": "Feature",
  "properties": {
    "gn:admin1_code":"3.0",
    "gn:asciiname":"Kabakai",
    "gn:country_code":"BW",
    "gn:dem":1131,
    "gn:feature_class":"P",
    "gn:feature_code":"PPL",
    "gn:name":"Kabakai",
    "gn:population":0,
    "gn:timezone":"Africa/Gaborone",
    "iso:country":"BW",
    "wof:name":"Kabakai",
    "wof:placetype":"locality"
},
  "geometry": {"coordinates":[21.68333,-21.71667],"type":"Point"}
}