{
  "type": "Feature",
  "properties": {
    "gn:admin1_code":"1.0",
    "gn:asciiname":"Phate",
    "gn:country_code":"BW",
    "gn:dem":1070,
    "gn:feature_class":"P",
    "gn:feature_code":"PPLL",
    "gn:name":"Phate",
    "gn:population":0,
    "gn:timezone":"Africa/Gaborone",
    "iso:country":"BW",
    "wof:name":"Phate",
    "wof:placetype":"locality"
},
  "geometry": {"coordinates":[26.65826,-22.67188],"type":"Point"}
}