{
  "type": "Feature",
  "properties": {
    "gn:admin1_code":"1.0",
    "gn:asciiname":"Thomadithotse",
    "gn:country_code":"BW",
    "gn:dem":1025,
    "gn:feature_class":"P",
    "gn:feature_code":"PPL",
    "gn:name":"Thomadithotse",
    "gn:population":0,
    "gn:timezone":"Africa/Gaborone",
    "iso:country":"BW",
    "wof:name":"Thomadithotse",
    "wof:placetype":"locality"
},
  "geometry": {"coordinates":[26.81421,-23.10407],"type":"Point"}
}