{
  "type": "Feature",
  "properties": {
    "iso:country":"BW",
    "name:cat_x_preferred":[
        "Kumakwane"
    ],
    "name:dut_x_preferred":[
        "Kumakwane"
    ],
    "name:eng_x_preferred":[
        "Kumakwane"
    ],
    "name:fas_x_preferred":[
        "\u06a9\u0648\u0645\u0627\u06a9\u0648\u0627\u0646\u060c \u0628\u0648\u062a\u0633\u0648\u0627\u0646\u0627"
    ],
    "name:fra_x_preferred":[
        "Kumakwane"
    ],
    "name:fre_x_preferred":[
        "Kumakwane"
    ],
    "name:ita_x_preferred":[
        "Kumakwane"
    ],
    "name:mlg_x_preferred":[
        "Kumakwane"
    ],
    "name:nld_x_preferred":[
        "Kumakwane"
    ],
    "name:oci_x_preferred":[
        "Kumakwane"
    ],
    "name:per_x_preferred":[
        "\u06a9\u0648\u0645\u0627\u06a9\u0648\u0627\u0646\u060c \u0628\u0648\u062a\u0633\u0648\u0627\u0646\u0627"
    ],
    "name:pol_x_preferred":[
        "Kumakwane"
    ],
    "name:rus_x_preferred":[
        "\u041a\u0443\u043c\u0430\u043a\u0432\u0430\u043d\u0435"
    ],
    "name:spa_x_preferred":[
        "Kumakwane"
    ],
    "name:swa_x_preferred":[
        "Kumakwane"
    ],
    "name:swe_x_preferred":[
        "Kumakwane"
    ],
    "qs:gn_country":"BW",
    "qs:gn_fcode":"PPL",
    "qs:gn_pop":0,
    "qs:name":"Kumakwane",
    "qs:name_adm0":"Botswana",
    "qs:name_adm1":"Kweneng",
    "qs:photos":19,
    "qs:photos_1k":4,
    "qs:photos_9k":1,
    "qs:photos_9r":1,
    "qs:photos_all":19,
    "qs:photos_sr":1,
    "qs:placetype":"Town",
    "qs:pop_sr":"0",
    "qs:woe_adm0":23424755,
    "wd:wordcount":75,
    "wof:name":"Kumakwane",
    "wof:placetype":"locality"
},
  "geometry": {"coordinates":[25.69918,-24.65522],"type":"Point"}
}