{
  "type": "Feature",
  "properties": {
    "gn:admin1_code":"1.0",
    "gn:asciiname":"Serojane",
    "gn:country_code":"BW",
    "gn:dem":912,
    "gn:feature_class":"P",
    "gn:feature_code":"PPL",
    "gn:name":"Serojane",
    "gn:population":0,
    "gn:timezone":"Africa/Gaborone",
    "iso:country":"BW",
    "wof:name":"Serojane",
    "wof:placetype":"locality"
},
  "geometry": {"coordinates":[26.76495,-23.42963],"type":"Point"}
}