{
  "type": "Feature",
  "properties": {
    "gn:admin1_code":"1.0",
    "gn:asciiname":"Motlhabaneng",
    "gn:country_code":"BW",
    "gn:dem":568,
    "gn:feature_class":"P",
    "gn:feature_code":"PPL",
    "gn:name":"Motlhabaneng",
    "gn:population":0,
    "gn:timezone":"Africa/Gaborone",
    "iso:country":"BW",
    "wof:name":"Motlhabaneng",
    "wof:placetype":"locality"
},
  "geometry": {"coordinates":[28.87859000000001,-22.17755],"type":"Point"}
}