{
  "type": "Feature",
  "properties": {
    "gn:admin1_code":"1.0",
    "gn:asciiname":"Mobotai",
    "gn:country_code":"BW",
    "gn:dem":796,
    "gn:feature_class":"P",
    "gn:feature_code":"PPLL",
    "gn:name":"Mobotai",
    "gn:population":0,
    "gn:timezone":"Africa/Gaborone",
    "iso:country":"BW",
    "wof:name":"Mobotai",
    "wof:placetype":"locality"
},
  "geometry": {"coordinates":[28.42695,-21.79119],"type":"Point"}
}