{
  "type": "Feature",
  "properties": {
    "gn:admin1_code":"5.0",
    "gn:asciiname":"Dikgama",
    "gn:country_code":"BW",
    "gn:dem":934,
    "gn:feature_class":"P",
    "gn:feature_code":"PPLL",
    "gn:name":"Dikgama",
    "gn:population":0,
    "gn:timezone":"Africa/Gaborone",
    "iso:country":"BW",
    "wof:name":"Dikgama",
    "wof:placetype":"locality"
},
  "geometry": {"coordinates":[26.32305,-24.12154],"type":"Point"}
}