{
  "type": "Feature",
  "properties": {
    "gn:admin1_code":"6.0",
    "gn:asciiname":"Tsorogwane",
    "gn:country_code":"BW",
    "gn:dem":1025,
    "gn:feature_class":"P",
    "gn:feature_code":"PPLL",
    "gn:name":"Tsorogwane",
    "gn:population":0,
    "gn:timezone":"Africa/Gaborone",
    "iso:country":"BW",
    "wof:name":"Tsorogwane",
    "wof:placetype":"locality"
},
  "geometry": {"coordinates":[25.69287000000001,-24.55555],"type":"Point"}
}