{
  "type": "Feature",
  "properties": {
    "gn:admin1_code":"10.0",
    "gn:asciiname":"Gamosinki",
    "gn:country_code":"BW",
    "gn:dem":1278,
    "gn:feature_class":"P",
    "gn:feature_code":"PPLL",
    "gn:name":"Gamosinki",
    "gn:population":0,
    "gn:timezone":"Africa/Gaborone",
    "iso:country":"BW",
    "wof:name":"Gamosinki",
    "wof:placetype":"locality"
},
  "geometry": {"coordinates":[25.20754,-25.14725],"type":"Point"}
}