{
  "type": "Feature",
  "properties": {
    "gn:admin1_code":"1.0",
    "gn:asciiname":"Sedimo",
    "gn:country_code":"BW",
    "gn:dem":906,
    "gn:feature_class":"P",
    "gn:feature_code":"PPLL",
    "gn:name":"Sedimo",
    "gn:population":0,
    "gn:timezone":"Africa/Gaborone",
    "iso:country":"BW",
    "wof:name":"Sedimo",
    "wof:placetype":"locality"
},
  "geometry": {"coordinates":[27.92796,-21.61751],"type":"Point"}
}