{
  "type": "Feature",
  "properties": {
    "gn:admin1_code":"1.0",
    "gn:asciiname":"Masiadieme",
    "gn:country_code":"BW",
    "gn:dem":760,
    "gn:feature_class":"P",
    "gn:feature_code":"PPL",
    "gn:name":"Masiadieme",
    "gn:population":0,
    "gn:timezone":"Africa/Gaborone",
    "iso:country":"BW",
    "wof:name":"Masiadieme",
    "wof:placetype":"locality"
},
  "geometry": {"coordinates":[28.35665,-22.06394],"type":"Point"}
}