{
  "type": "Feature",
  "properties": {
    "gn:admin1_code":"1.0",
    "gn:asciiname":"Thabatskudu",
    "gn:country_code":"BW",
    "gn:dem":904,
    "gn:feature_class":"P",
    "gn:feature_code":"PPL",
    "gn:name":"Thabatskudu",
    "gn:population":0,
    "gn:timezone":"Africa/Gaborone",
    "iso:country":"BW",
    "wof:name":"Thabatskudu",
    "wof:placetype":"locality"
},
  "geometry": {"coordinates":[25.76667,-20.73333],"type":"Point"}
}