{
  "type": "Feature",
  "properties": {
    "gn:admin1_code":"10.0",
    "gn:asciiname":"Matlakeng",
    "gn:country_code":"BW",
    "gn:dem":1206,
    "gn:feature_class":"P",
    "gn:feature_code":"PPLL",
    "gn:name":"Matlakeng",
    "gn:population":0,
    "gn:timezone":"Africa/Gaborone",
    "iso:country":"BW",
    "wof:name":"Matlakeng",
    "wof:placetype":"locality"
},
  "geometry": {"coordinates":[25.21547,-25.63959],"type":"Point"}
}