{
  "type": "Feature",
  "properties": {
    "gn:admin1_code":"0.0",
    "gn:asciiname":"Nekati",
    "gn:country_code":"BW",
    "gn:dem":920,
    "gn:feature_class":"P",
    "gn:feature_code":"PPL",
    "gn:name":"Nekati",
    "gn:population":0,
    "gn:timezone":"Africa/Gaborone",
    "iso:country":"BW",
    "wof:name":"Nekati",
    "wof:placetype":"locality"
},
  "geometry": {"coordinates":[26.01667,-20.08333],"type":"Point"}
}