{
  "type": "Feature",
  "properties": {
    "gn:admin1_code":"1.0",
    "gn:asciiname":"Ramokgweng",
    "gn:country_code":"BW",
    "gn:dem":1031,
    "gn:feature_class":"P",
    "gn:feature_code":"PPL",
    "gn:name":"Ramokgweng",
    "gn:population":0,
    "gn:timezone":"Africa/Gaborone",
    "iso:country":"BW",
    "wof:name":"Ramokgweng",
    "wof:placetype":"locality"
},
  "geometry": {"coordinates":[26.00756,-21.32382],"type":"Point"}
}