{
  "type": "Feature",
  "properties": {
    "gn:admin1_code":"0.0",
    "gn:asciiname":"Motloutse",
    "gn:cc2":"BW",
    "gn:country_code":"BW",
    "gn:dem":723,
    "gn:feature_class":"P",
    "gn:feature_code":"PPL",
    "gn:name":"Motloutse",
    "gn:population":0,
    "gn:timezone":"Africa/Gaborone",
    "iso:country":"BW",
    "name:und_x_variant":[
        "Maklauts",
        "Maklautsi",
        "Motloutse"
    ],
    "wof:name":"Motloutse",
    "wof:placetype":"locality"
},
  "geometry": {"coordinates":[28.41667,-22.01667],"type":"Point"}
}