{
  "type": "Feature",
  "properties": {
    "gn:admin1_code":"1.0",
    "gn:asciiname":"Madiba",
    "gn:country_code":"BW",
    "gn:dem":1034,
    "gn:feature_class":"P",
    "gn:feature_code":"PPLL",
    "gn:name":"Madiba",
    "gn:population":0,
    "gn:timezone":"Africa/Gaborone",
    "iso:country":"BW",
    "wof:name":"Madiba",
    "wof:placetype":"locality"
},
  "geometry": {"coordinates":[26.80148,-23.06963],"type":"Point"}
}