{
  "type": "Feature",
  "properties": {
    "gn:admin1_code":"10.0",
    "gn:asciiname":"Gamoswaana",
    "gn:country_code":"BW",
    "gn:dem":1195,
    "gn:feature_class":"P",
    "gn:feature_code":"PPLL",
    "gn:name":"Gamoswaana",
    "gn:population":0,
    "gn:timezone":"Africa/Gaborone",
    "iso:country":"BW",
    "wof:name":"Gamoswaana",
    "wof:placetype":"locality"
},
  "geometry": {"coordinates":[25.49012,-25.10843],"type":"Point"}
}