{
  "type": "Feature",
  "properties": {
    "gn:admin1_code":"10.0",
    "gn:asciiname":"Motlhahuneng",
    "gn:country_code":"BW",
    "gn:dem":1342,
    "gn:feature_class":"P",
    "gn:feature_code":"PPLL",
    "gn:name":"Motlhahuneng",
    "gn:population":0,
    "gn:timezone":"Africa/Gaborone",
    "iso:country":"BW",
    "wof:name":"Motlhahuneng",
    "wof:placetype":"locality"
},
  "geometry": {"coordinates":[25.18505,-24.97999],"type":"Point"}
}