{
  "type": "Feature",
  "properties": {
    "gn:admin1_code":"1.0",
    "gn:asciiname":"Mookametsana",
    "gn:country_code":"BW",
    "gn:dem":930,
    "gn:feature_class":"P",
    "gn:feature_code":"PPL",
    "gn:name":"Mookametsana",
    "gn:population":0,
    "gn:timezone":"Africa/Gaborone",
    "iso:country":"BW",
    "wof:name":"Mookametsana",
    "wof:placetype":"locality"
},
  "geometry": {"coordinates":[27.27935,-23.15763],"type":"Point"}
}