{
  "type": "Feature",
  "properties": {
    "gn:admin1_code":"10.0",
    "gn:asciiname":"Pitsane",
    "gn:country_code":"BW",
    "gn:dem":1167,
    "gn:feature_class":"P",
    "gn:feature_code":"PPLL",
    "gn:name":"Pitsane",
    "gn:population":0,
    "gn:timezone":"Africa/Gaborone",
    "iso:country":"BW",
    "wof:name":"Pitsane",
    "wof:placetype":"locality"
},
  "geometry": {"coordinates":[25.45997,-24.98275],"type":"Point"}
}