{
  "type": "Feature",
  "properties": {
    "gn:admin1_code":"10.0",
    "gn:asciiname":"Monnamme",
    "gn:country_code":"BW",
    "gn:dem":1122,
    "gn:feature_class":"P",
    "gn:feature_code":"PPLL",
    "gn:name":"Monnamme",
    "gn:population":0,
    "gn:timezone":"Africa/Gaborone",
    "iso:country":"BW",
    "wof:name":"Monnamme",
    "wof:placetype":"locality"
},
  "geometry": {"coordinates":[25.44459,-24.82924],"type":"Point"}
}