{
  "type": "Feature",
  "properties": {
    "gn:admin1_code":"10.0",
    "gn:asciiname":"Bulukubalo",
    "gn:country_code":"BW",
    "gn:dem":1093,
    "gn:feature_class":"P",
    "gn:feature_code":"PPL",
    "gn:name":"Bulukubalo",
    "gn:population":0,
    "gn:timezone":"Africa/Gaborone",
    "iso:country":"BW",
    "wof:name":"Bulukubalo",
    "wof:placetype":"locality"
},
  "geometry": {"coordinates":[23.31667,-24.23333],"type":"Point"}
}