{
  "type": "Feature",
  "properties": {
    "gn:admin1_code":"1.0",
    "gn:asciiname":"Natale",
    "gn:country_code":"BW",
    "gn:dem":1036,
    "gn:feature_class":"P",
    "gn:feature_code":"PPL",
    "gn:name":"Natale",
    "gn:population":0,
    "gn:timezone":"Africa/Gaborone",
    "iso:country":"BW",
    "wof:name":"Natale",
    "wof:placetype":"locality"
},
  "geometry": {"coordinates":[27.22561,-21.10274],"type":"Point"}
}