{
  "type": "Feature",
  "properties": {
    "gn:admin1_code":"6.0",
    "gn:asciiname":"Mohukutshwane",
    "gn:country_code":"BW",
    "gn:dem":1145,
    "gn:feature_class":"P",
    "gn:feature_code":"PPLL",
    "gn:name":"Mohukutshwane",
    "gn:population":0,
    "gn:timezone":"Africa/Gaborone",
    "iso:country":"BW",
    "wof:name":"Mohukutshwane",
    "wof:placetype":"locality"
},
  "geometry": {"coordinates":[25.58885,-24.39011],"type":"Point"}
}