{
  "type": "Feature",
  "properties": {
    "gn:admin1_code":"1.0",
    "gn:asciiname":"Mabolobolo",
    "gn:country_code":"BW",
    "gn:dem":892,
    "gn:feature_class":"P",
    "gn:feature_code":"PPLL",
    "gn:name":"Mabolobolo",
    "gn:population":0,
    "gn:timezone":"Africa/Gaborone",
    "iso:country":"BW",
    "wof:name":"Mabolobolo",
    "wof:placetype":"locality"
},
  "geometry": {"coordinates":[27.51991,-22.78518],"type":"Point"}
}