{
  "type": "Feature",
  "properties": {
    "gn:admin1_code":"10.0",
    "gn:asciiname":"Letsopa",
    "gn:country_code":"BW",
    "gn:dem":1258,
    "gn:feature_class":"P",
    "gn:feature_code":"PPLL",
    "gn:name":"Letsopa",
    "gn:population":0,
    "gn:timezone":"Africa/Gaborone",
    "iso:country":"BW",
    "wof:name":"Letsopa",
    "wof:placetype":"locality"
},
  "geometry": {"coordinates":[25.31002,-25.25004],"type":"Point"}
}