{
  "type": "Feature",
  "properties": {
    "gn:admin1_code":"0.0",
    "gn:asciiname":"Lambeye",
    "gn:country_code":"BW",
    "gn:dem":931,
    "gn:feature_class":"P",
    "gn:feature_code":"PPL",
    "gn:name":"Lambeye",
    "gn:population":0,
    "gn:timezone":"Africa/Gaborone",
    "iso:country":"BW",
    "wof:name":"Lambeye",
    "wof:placetype":"locality"
},
  "geometry": {"coordinates":[24.63333,-17.96667],"type":"Point"}
}