{
  "type": "Feature",
  "properties": {
    "gn:admin1_code":"8.0",
    "gn:asciiname":"Habangan",
    "gn:country_code":"BW",
    "gn:dem":1287,
    "gn:feature_class":"P",
    "gn:feature_code":"PPL",
    "gn:name":"Habangan",
    "gn:population":0,
    "gn:timezone":"Africa/Gaborone",
    "iso:country":"BW",
    "name:und_x_variant":[
        "Habangana",
        "Mapoka"
    ],
    "wof:name":"Habangan",
    "wof:placetype":"locality"
},
  "geometry": {"coordinates":[27.58901,-20.53804],"type":"Point"}
}