{
  "type": "Feature",
  "properties": {
    "gn:admin1_code":"1.0",
    "gn:asciiname":"Mabeleapodi",
    "gn:country_code":"BW",
    "gn:dem":1176,
    "gn:feature_class":"P",
    "gn:feature_code":"PPL",
    "gn:name":"Mabeleapodi",
    "gn:population":0,
    "gn:timezone":"Africa/Gaborone",
    "iso:country":"BW",
    "name:und_x_variant":[
        "Mabeleapudi"
    ],
    "wof:name":"Mabeleapodi",
    "wof:placetype":"locality"
},
  "geometry": {"coordinates":[26.83312,-22.21355],"type":"Point"}
}