{
  "type": "Feature",
  "properties": {
    "gn:admin1_code":"1.0",
    "gn:asciiname":"Dinokana",
    "gn:country_code":"BW",
    "gn:dem":932,
    "gn:feature_class":"P",
    "gn:feature_code":"PPL",
    "gn:name":"Dinokana",
    "gn:population":0,
    "gn:timezone":"Africa/Gaborone",
    "iso:country":"BW",
    "wof:name":"Dinokana",
    "wof:placetype":"locality"
},
  "geometry": {"coordinates":[26.28015,-21.01359],"type":"Point"}
}