{
  "type": "Feature",
  "properties": {
    "gn:admin1_code":"1.0",
    "gn:asciiname":"Bodungwe",
    "gn:country_code":"BW",
    "gn:dem":924,
    "gn:feature_class":"P",
    "gn:feature_code":"PPLL",
    "gn:name":"Bodungwe",
    "gn:population":0,
    "gn:timezone":"Africa/Gaborone",
    "iso:country":"BW",
    "wof:name":"Bodungwe",
    "wof:placetype":"locality"
},
  "geometry": {"coordinates":[27.06451,-23.23534],"type":"Point"}
}