{
  "type": "Feature",
  "properties": {
    "gn:admin1_code":"5.0",
    "gn:asciiname":"Lentsweng",
    "gn:country_code":"BW",
    "gn:dem":952,
    "gn:feature_class":"P",
    "gn:feature_code":"PPL",
    "gn:name":"Lentsweng",
    "gn:population":0,
    "gn:timezone":"Africa/Gaborone",
    "iso:country":"BW",
    "wof:name":"Lentsweng",
    "wof:placetype":"locality"
},
  "geometry": {"coordinates":[26.29279,-23.86333],"type":"Point"}
}