{
  "type": "Feature",
  "properties": {
    "gn:admin1_code":"1.0",
    "gn:asciiname":"Molekaletabo",
    "gn:country_code":"BW",
    "gn:dem":856,
    "gn:feature_class":"P",
    "gn:feature_code":"PPLL",
    "gn:name":"Molekaletabo",
    "gn:population":0,
    "gn:timezone":"Africa/Gaborone",
    "iso:country":"BW",
    "wof:name":"Molekaletabo",
    "wof:placetype":"locality"
},
  "geometry": {"coordinates":[27.5971,-22.89767],"type":"Point"}
}