{
  "type": "Feature",
  "properties": {
    "gn:admin1_code":"1.0",
    "gn:asciiname":"Chiwelo",
    "gn:country_code":"BW",
    "gn:dem":960,
    "gn:feature_class":"P",
    "gn:feature_code":"PPLL",
    "gn:name":"Chiwelo",
    "gn:population":0,
    "gn:timezone":"Africa/Gaborone",
    "iso:country":"BW",
    "name:und_x_variant":[
        "Chuela"
    ],
    "wof:name":"Chiwelo",
    "wof:placetype":"locality"
},
  "geometry": {"coordinates":[27.20803,-23.01171],"type":"Point"}
}