{
  "type": "Feature",
  "properties": {
    "gn:admin1_code":"1.0",
    "gn:asciiname":"Matikwe",
    "gn:country_code":"BW",
    "gn:dem":1230,
    "gn:feature_class":"P",
    "gn:feature_code":"PPLL",
    "gn:name":"Matikwe",
    "gn:population":0,
    "gn:timezone":"Africa/Gaborone",
    "iso:country":"BW",
    "wof:name":"Matikwe",
    "wof:placetype":"locality"
},
  "geometry": {"coordinates":[26.58621,-22.15487000000001],"type":"Point"}
}