{
  "type": "Feature",
  "properties": {
    "gn:admin1_code":"6.0",
    "gn:asciiname":"Thakatswane",
    "gn:country_code":"BW",
    "gn:dem":1016,
    "gn:feature_class":"P",
    "gn:feature_code":"PPLL",
    "gn:name":"Thakatswane",
    "gn:population":0,
    "gn:timezone":"Africa/Gaborone",
    "iso:country":"BW",
    "wof:name":"Thakatswane",
    "wof:placetype":"locality"
},
  "geometry": {"coordinates":[25.90162,-24.16163],"type":"Point"}
}