{
  "type": "Feature",
  "properties": {
    "iso:country":"BW",
    "name:ceb_x_preferred":[
        "Mogoditshane"
    ],
    "name:deu_x_preferred":[
        "Mogoditshane"
    ],
    "name:ell_x_preferred":[
        "\u039c\u03bf\u03b3\u03ba\u03bf\u03bd\u03c4\u03b9\u03c4\u03c3\u03ac\u03bd\u03b5"
    ],
    "name:eng_x_preferred":[
        "Mogoditshane"
    ],
    "name:epo_x_preferred":[
        "Mogoditshane"
    ],
    "name:eus_x_preferred":[
        "Mogoditshane"
    ],
    "name:fas_x_preferred":[
        "\u0645\u0648\u06af\u0648\u062f\u06cc\u062a\u0634\u0627\u0646\u060c \u0628\u0648\u062a\u0633\u0648\u0627\u0646\u0627"
    ],
    "name:fra_x_preferred":[
        "Mogoditshane"
    ],
    "name:hrv_x_preferred":[
        "Mogoditshane"
    ],
    "name:ita_x_preferred":[
        "Mogoditshane"
    ],
    "name:jpn_x_preferred":[
        "\u30e2\u30db\u30c7\u30a3\u30c4\u30a1\u30cd"
    ],
    "name:mlg_x_preferred":[
        "Mogoditshane"
    ],
    "name:nld_x_preferred":[
        "Mogoditshane"
    ],
    "name:nob_x_preferred":[
        "Mogoditshane"
    ],
    "name:nor_x_preferred":[
        "Mogoditshane"
    ],
    "name:pol_x_preferred":[
        "Mogoditshane"
    ],
    "name:por_x_preferred":[
        "Mogoditshane"
    ],
    "name:ron_x_preferred":[
        "Mogoditshane"
    ],
    "name:rus_x_preferred":[
        "\u041c\u043e\u0433\u043e\u0434\u0438\u0447\u0430\u043d\u0435"
    ],
    "name:spa_x_preferred":[
        "Mogoditshane"
    ],
    "name:swa_x_preferred":[
        "Mogoditshane"
    ],
    "name:swe_x_preferred":[
        "Mogoditshane"
    ],
    "name:tsn_x_preferred":[
        "Mogoditshane"
    ],
    "name:tur_x_preferred":[
        "Mogoditshane"
    ],
    "name:unk_x_variant":[
        "Mogoditsane"
    ],
    "name:vep_x_preferred":[
        "Mogodit\u0161ane"
    ],
    "name:zho_x_preferred":[
        "\u83ab\u6208\u8fea\u6c99\u5167"
    ],
    "qs:gn_country":"BW",
    "qs:gn_fcode":"PPL",
    "qs:gn_pop":43394,
    "qs:name":"Mogoditshane",
    "qs:name_adm0":"Botswana",
    "qs:name_adm1":"Kweneng",
    "qs:photos":0,
    "qs:photos_1k":0,
    "qs:photos_9k":2,
    "qs:photos_9r":5,
    "qs:photos_all":357,
    "qs:photos_sr":0,
    "qs:placetype":"Town",
    "qs:pop_sr":"7",
    "qs:woe_adm0":23424755,
    "wd:elevation":1022.0,
    "wd:wordcount":74,
    "wof:name":"Mogoditshane",
    "wof:placetype":"locality",
    "wof:population":43394
},
  "geometry": {"coordinates":[25.86556,-24.62694],"type":"Point"}
}