{
  "type": "Feature",
  "properties": {
    "gn:country":"BW",
    "gn:fcode":"PPL",
    "gn:population":1515,
    "iso:country":"BW",
    "name:ceb_x_preferred":[
        "Mogapinyana"
    ],
    "name:eng_x_preferred":[
        "Mogapinyana"
    ],
    "name:fra_x_preferred":[
        "Mogapinyana"
    ],
    "name:ita_x_preferred":[
        "Mogapinyana"
    ],
    "name:mlg_x_preferred":[
        "Mogapinyana"
    ],
    "name:nld_x_preferred":[
        "Mogapinyana"
    ],
    "name:pol_x_preferred":[
        "Mogapinyana"
    ],
    "name:swa_x_preferred":[
        "Mogapinyana"
    ],
    "name:swe_x_preferred":[
        "Mogapinyana"
    ],
    "qs:name":"Mogapinyana",
    "qs:photos_9r":0,
    "qs:photos_sr":0,
    "qs:pop_sr":"3",
    "wd:wordcount":74,
    "wof:name":"Mogapinyana",
    "wof:placetype":"locality",
    "wof:population":1515
},
  "geometry": {"coordinates":[27.6,-22.36667],"type":"Point"}
}