{
  "type": "Feature",
  "properties": {
    "gn:admin1_code":"0.0",
    "gn:asciiname":"Segara",
    "gn:country_code":"BW",
    "gn:dem":927,
    "gn:feature_class":"P",
    "gn:feature_code":"PPL",
    "gn:name":"Segara",
    "gn:population":0,
    "gn:timezone":"Africa/Gaborone",
    "iso:country":"BW",
    "wof:name":"Segara",
    "wof:placetype":"locality"
},
  "geometry": {"coordinates":[25.26667,-20.23333],"type":"Point"}
}