{
  "type": "Feature",
  "properties": {
    "gn:admin1_code":"1.0",
    "gn:asciiname":"Letsibogo",
    "gn:country_code":"BW",
    "gn:dem":817,
    "gn:feature_class":"P",
    "gn:feature_code":"PPLL",
    "gn:name":"Letsibogo",
    "gn:population":0,
    "gn:timezone":"Africa/Gaborone",
    "iso:country":"BW",
    "wof:name":"Letsibogo",
    "wof:placetype":"locality"
},
  "geometry": {"coordinates":[27.86246,-22.59465],"type":"Point"}
}