{
  "type": "Feature",
  "properties": {
    "gn:country":"BW",
    "gn:fcode":"PPL",
    "gn:population":1277,
    "iso:country":"BW",
    "name:ceb_x_preferred":[
        "Pilane"
    ],
    "name:eng_x_preferred":[
        "Pilane"
    ],
    "name:fra_x_preferred":[
        "Pilane Station"
    ],
    "name:ita_x_preferred":[
        "Pilane Station"
    ],
    "name:mlg_x_preferred":[
        "Pilane Station"
    ],
    "name:nld_x_preferred":[
        "Pilane Station"
    ],
    "name:pol_x_preferred":[
        "Pilane Station"
    ],
    "name:rus_x_preferred":[
        "\u041f\u0438\u043b\u0430\u043d\u0435"
    ],
    "name:swa_x_preferred":[
        "Pilane Station"
    ],
    "name:swe_x_preferred":[
        "Pilane"
    ],
    "name:tsn_x_preferred":[
        "Pilane"
    ],
    "qs:name":"Pilane",
    "qs:photos_9r":0,
    "qs:photos_sr":0,
    "qs:pop_sr":"3",
    "wd:wordcount":8,
    "wof:name":"Pilane",
    "wof:placetype":"locality",
    "wof:population":1277
},
  "geometry": {"coordinates":[26.13333,-24.45],"type":"Point"}
}