{
  "type": "Feature",
  "properties": {
    "gn:country":"BW",
    "gn:fcode":"PPL",
    "gn:population":16853,
    "iso:country":"BW",
    "qs:name":"Janeng",
    "qs:photos_9r":0,
    "qs:photos_sr":0,
    "qs:pop_sr":"6",
    "wof:name":"Janeng",
    "wof:placetype":"locality",
    "wof:population":16853
},
  "geometry": {"coordinates":[25.55,-25.41667],"type":"Point"}
}