{
  "type": "Feature",
  "properties": {
    "gn:admin1_code":"1.0",
    "gn:asciiname":"Mabolwe",
    "gn:country_code":"BW",
    "gn:dem":716,
    "gn:feature_class":"P",
    "gn:feature_code":"PPL",
    "gn:name":"Mabolwe",
    "gn:population":0,
    "gn:timezone":"Africa/Gaborone",
    "iso:country":"BW",
    "name:ceb_x_preferred":[
        "Mabolwe"
    ],
    "name:fra_x_preferred":[
        "Mabolwe"
    ],
    "name:ita_x_preferred":[
        "Mabolwe"
    ],
    "name:mlg_x_preferred":[
        "Mabolwe"
    ],
    "name:nld_x_preferred":[
        "Mabolwe"
    ],
    "name:pol_x_preferred":[
        "Mabolwe"
    ],
    "name:swa_x_preferred":[
        "Mabolwe"
    ],
    "name:swe_x_preferred":[
        "Mabolwe"
    ],
    "wof:name":"Mabolwe",
    "wof:placetype":"locality"
},
  "geometry": {"coordinates":[28.82004,-21.82117],"type":"Point"}
}