{
  "type": "Feature",
  "properties": {
    "gn:admin1_code":"1.0",
    "gn:asciiname":"Gobosholo",
    "gn:country_code":"BW",
    "gn:dem":958,
    "gn:feature_class":"P",
    "gn:feature_code":"PPLL",
    "gn:name":"Gobosholo",
    "gn:population":0,
    "gn:timezone":"Africa/Gaborone",
    "iso:country":"BW",
    "wof:name":"Gobosholo",
    "wof:placetype":"locality"
},
  "geometry": {"coordinates":[27.46862,-21.58723],"type":"Point"}
}