{
  "type": "Feature",
  "properties": {
    "gn:admin1_code":"5.0",
    "gn:asciiname":"Lerula",
    "gn:country_code":"BW",
    "gn:dem":890,
    "gn:feature_class":"P",
    "gn:feature_code":"PPL",
    "gn:name":"Lerula",
    "gn:population":0,
    "gn:timezone":"Africa/Gaborone",
    "iso:country":"BW",
    "wof:name":"Lerula",
    "wof:placetype":"locality"
},
  "geometry": {"coordinates":[26.59439,-23.96217],"type":"Point"}
}