{
  "type": "Feature",
  "properties": {
    "gn:admin1_code":"1.0",
    "gn:asciiname":"Mmamhatane",
    "gn:country_code":"BW",
    "gn:dem":906,
    "gn:feature_class":"P",
    "gn:feature_code":"PPLL",
    "gn:name":"Mmamhatane",
    "gn:population":0,
    "gn:timezone":"Africa/Gaborone",
    "iso:country":"BW",
    "wof:name":"Mmamhatane",
    "wof:placetype":"locality"
},
  "geometry": {"coordinates":[27.53463,-22.74072],"type":"Point"}
}