{
  "type": "Feature",
  "properties": {
    "gn:admin1_code":"1.0",
    "gn:asciiname":"Metsingmahibidu",
    "gn:country_code":"BW",
    "gn:dem":1269,
    "gn:feature_class":"P",
    "gn:feature_code":"PPLL",
    "gn:name":"Metsingmahibidu",
    "gn:population":0,
    "gn:timezone":"Africa/Gaborone",
    "iso:country":"BW",
    "wof:name":"Metsingmahibidu",
    "wof:placetype":"locality"
},
  "geometry": {"coordinates":[26.37299,-22.87646],"type":"Point"}
}