{
  "type": "Feature",
  "properties": {
    "gn:admin1_code":"0.0",
    "gn:asciiname":"Mokaya",
    "gn:country_code":"BW",
    "gn:dem":968,
    "gn:feature_class":"P",
    "gn:feature_code":"PPL",
    "gn:name":"Mokaya",
    "gn:population":0,
    "gn:timezone":"Africa/Gaborone",
    "iso:country":"BW",
    "name:deu_x_preferred":[
        "Mokaya-Kultur"
    ],
    "name:fin_x_preferred":[
        "Mokaya"
    ],
    "name:fra_x_preferred":[
        "Mokaya"
    ],
    "wof:name":"Mokaya",
    "wof:placetype":"locality"
},
  "geometry": {"coordinates":[22.71667,-18.91667],"type":"Point"}
}