{
  "type": "Feature",
  "properties": {
    "gn:admin1_code":"0.0",
    "gn:asciiname":"Kuke",
    "gn:cc2":"BW",
    "gn:country_code":"BW",
    "gn:dem":1000,
    "gn:feature_class":"P",
    "gn:feature_code":"PPL",
    "gn:name":"Kuke",
    "gn:population":0,
    "gn:timezone":"Africa/Gaborone",
    "iso:country":"BW",
    "name:ceb_x_preferred":[
        "Kuke"
    ],
    "name:ces_x_preferred":[
        "Kuke"
    ],
    "name:deu_x_preferred":[
        "Kuke"
    ],
    "name:est_x_preferred":[
        "Kuke"
    ],
    "name:nld_x_preferred":[
        "Kuke"
    ],
    "name:pol_x_preferred":[
        "Kuke"
    ],
    "name:swe_x_preferred":[
        "Kuke"
    ],
    "name:und_x_variant":[
        "Kuki",
        "Kuke"
    ],
    "name:vol_x_preferred":[
        "Kuke"
    ],
    "wof:name":"Kuke",
    "wof:placetype":"locality"
},
  "geometry": {"coordinates":[24.48333,-23.31667],"type":"Point"}
}