{
  "type": "Feature",
  "properties": {
    "gn:admin1_code":"1.0",
    "gn:asciiname":"Mmapilane",
    "gn:country_code":"BW",
    "gn:dem":1182,
    "gn:feature_class":"P",
    "gn:feature_code":"PPLL",
    "gn:name":"Mmapilane",
    "gn:population":0,
    "gn:timezone":"Africa/Gaborone",
    "iso:country":"BW",
    "wof:name":"Mmapilane",
    "wof:placetype":"locality"
},
  "geometry": {"coordinates":[26.41988,-22.52667000000001],"type":"Point"}
}