{
  "type": "Feature",
  "properties": {
    "gn:admin1_code":"1.0",
    "gn:asciiname":"Ikongwe",
    "gn:country_code":"BW",
    "gn:dem":1067,
    "gn:feature_class":"P",
    "gn:feature_code":"PPL",
    "gn:name":"Ikongwe",
    "gn:population":0,
    "gn:timezone":"Africa/Gaborone",
    "iso:country":"BW",
    "name:fra_x_preferred":[
        "Ikongwe"
    ],
    "name:ita_x_preferred":[
        "Ikongwe"
    ],
    "name:mlg_x_preferred":[
        "Ikongwe"
    ],
    "name:nld_x_preferred":[
        "Ikongwe"
    ],
    "name:pol_x_preferred":[
        "Ikongwe"
    ],
    "name:swa_x_preferred":[
        "Ikongwe"
    ],
    "name:swe_x_preferred":[
        "Ikongwe"
    ],
    "name:tsn_x_preferred":[
        "Ikongwe"
    ],
    "wof:name":"Ikongwe",
    "wof:placetype":"locality"
},
  "geometry": {"coordinates":[26.42269000000001,-23.13563],"type":"Point"}
}