{
  "type": "Feature",
  "properties": {
    "gn:admin1_code":"6.0",
    "gn:asciiname":"Morungwane",
    "gn:country_code":"BW",
    "gn:dem":1090,
    "gn:feature_class":"P",
    "gn:feature_code":"PPLL",
    "gn:name":"Morungwane",
    "gn:population":0,
    "gn:timezone":"Africa/Gaborone",
    "iso:country":"BW",
    "wof:name":"Morungwane",
    "wof:placetype":"locality"
},
  "geometry": {"coordinates":[25.71946,-24.28764],"type":"Point"}
}