{
  "type": "Feature",
  "properties": {
    "gn:admin1_code":"10.0",
    "gn:asciiname":"Gatsepane",
    "gn:country_code":"BW",
    "gn:dem":1103,
    "gn:feature_class":"P",
    "gn:feature_code":"PPLL",
    "gn:name":"Gatsepane",
    "gn:population":0,
    "gn:timezone":"Africa/Gaborone",
    "iso:country":"BW",
    "wof:name":"Gatsepane",
    "wof:placetype":"locality"
},
  "geometry": {"coordinates":[25.43324,-24.79108],"type":"Point"}
}