{
  "type": "Feature",
  "properties": {
    "gn:admin1_code":"10.0",
    "gn:asciiname":"Mogojwagojwe",
    "gn:country_code":"BW",
    "gn:dem":1288,
    "gn:feature_class":"P",
    "gn:feature_code":"PPL",
    "gn:name":"Mogojwagojwe",
    "gn:population":0,
    "gn:timezone":"Africa/Gaborone",
    "iso:country":"BW",
    "wof:name":"Mogojwagojwe",
    "wof:placetype":"locality"
},
  "geometry": {"coordinates":[25.47551,-25.29246],"type":"Point"}
}