{
  "type": "Feature",
  "properties": {
    "gn:admin1_code":"1.0",
    "gn:asciiname":"Mmammedi",
    "gn:country_code":"BW",
    "gn:dem":863,
    "gn:feature_class":"P",
    "gn:feature_code":"PPLL",
    "gn:name":"Mmammedi",
    "gn:population":0,
    "gn:timezone":"Africa/Gaborone",
    "iso:country":"BW",
    "wof:name":"Mmammedi",
    "wof:placetype":"locality"
},
  "geometry": {"coordinates":[28.26381,-21.6605],"type":"Point"}
}