{
  "type": "Feature",
  "properties": {
    "gn:admin1_code":"10.0",
    "gn:asciiname":"Tsokwane",
    "gn:country_code":"BW",
    "gn:dem":1311,
    "gn:feature_class":"P",
    "gn:feature_code":"PPLL",
    "gn:name":"Tsokwane",
    "gn:population":0,
    "gn:timezone":"Africa/Gaborone",
    "iso:country":"BW",
    "wof:name":"Tsokwane",
    "wof:placetype":"locality"
},
  "geometry": {"coordinates":[25.28737000000001,-25.10458],"type":"Point"}
}