{
  "type": "Feature",
  "properties": {
    "gn:admin1_code":"10.0",
    "gn:asciiname":"Ntlhantlhe",
    "gn:country_code":"BW",
    "gn:dem":1102,
    "gn:feature_class":"P",
    "gn:feature_code":"PPL",
    "gn:name":"Ntlhantlhe",
    "gn:population":0,
    "gn:timezone":"Africa/Gaborone",
    "iso:country":"BW",
    "wof:name":"Ntlhantlhe",
    "wof:placetype":"locality"
},
  "geometry": {"coordinates":[25.59398,-24.96317],"type":"Point"}
}