{
  "type": "Feature",
  "properties": {
    "gn:admin1_code":"1.0",
    "gn:asciiname":"Magothong",
    "gn:country_code":"BW",
    "gn:dem":733,
    "gn:feature_class":"P",
    "gn:feature_code":"PPLL",
    "gn:name":"Magothong",
    "gn:population":0,
    "gn:timezone":"Africa/Gaborone",
    "iso:country":"BW",
    "wof:name":"Magothong",
    "wof:placetype":"locality"
},
  "geometry": {"coordinates":[28.37415,-22.11718],"type":"Point"}
}