{
  "type": "Feature",
  "properties": {
    "gn:admin1_code":"1.0",
    "gn:asciiname":"Mathape",
    "gn:country_code":"BW",
    "gn:dem":1045,
    "gn:feature_class":"P",
    "gn:feature_code":"PPLL",
    "gn:name":"Mathape",
    "gn:population":0,
    "gn:timezone":"Africa/Gaborone",
    "iso:country":"BW",
    "wof:name":"Mathape",
    "wof:placetype":"locality"
},
  "geometry": {"coordinates":[26.79819,-22.69657],"type":"Point"}
}