{
  "type": "Feature",
  "properties": {
    "gn:admin1_code":"6.0",
    "gn:asciiname":"Bohutsana",
    "gn:country_code":"BW",
    "gn:dem":1059,
    "gn:feature_class":"P",
    "gn:feature_code":"PPLL",
    "gn:name":"Bohutsana",
    "gn:population":0,
    "gn:timezone":"Africa/Gaborone",
    "iso:country":"BW",
    "wof:name":"Bohutsana",
    "wof:placetype":"locality"
},
  "geometry": {"coordinates":[25.76587,-24.03919],"type":"Point"}
}