{
  "type": "Feature",
  "properties": {
    "gn:admin1_code":"1.0",
    "gn:asciiname":"Lentswelekgoro",
    "gn:country_code":"BW",
    "gn:dem":825,
    "gn:feature_class":"P",
    "gn:feature_code":"PPLL",
    "gn:name":"Lentswelekgoro",
    "gn:population":0,
    "gn:timezone":"Africa/Gaborone",
    "iso:country":"BW",
    "wof:name":"Lentswelekgoro",
    "wof:placetype":"locality"
},
  "geometry": {"coordinates":[28.23094,-21.61102],"type":"Point"}
}