{
  "type": "Feature",
  "properties": {
    "gn:admin1_code":"9.0",
    "gn:asciiname":"Phakalane",
    "gn:country_code":"BW",
    "gn:dem":1005,
    "gn:feature_class":"P",
    "gn:feature_code":"PPL",
    "gn:name":"Phakalane",
    "gn:population":0,
    "gn:timezone":"Africa/Gaborone",
    "iso:country":"BW",
    "wof:name":"Phakalane",
    "wof:placetype":"locality"
},
  "geometry": {"coordinates":[25.95159,-24.56078],"type":"Point"}
}