{
  "type": "Feature",
  "properties": {
    "gn:admin1_code":"1.0",
    "gn:asciiname":"Tshokwe",
    "gn:country_code":"BW",
    "gn:dem":860,
    "gn:feature_class":"P",
    "gn:feature_code":"PPLL",
    "gn:name":"Tshokwe",
    "gn:population":0,
    "gn:timezone":"Africa/Gaborone",
    "iso:country":"BW",
    "name:ceb_x_preferred":[
        "Tshokwe"
    ],
    "name:fra_x_preferred":[
        "Tshokwe"
    ],
    "name:ita_x_preferred":[
        "Tshokwe"
    ],
    "name:mlg_x_preferred":[
        "Tshokwe"
    ],
    "name:nld_x_preferred":[
        "Tshokwe"
    ],
    "name:pol_x_preferred":[
        "Tshokwe"
    ],
    "name:swa_x_preferred":[
        "Tshokwe"
    ],
    "name:swe_x_preferred":[
        "Tshokwe"
    ],
    "wof:name":"Tshokwe",
    "wof:placetype":"locality"
},
  "geometry": {"coordinates":[28.10971,-21.71377],"type":"Point"}
}