{
  "type": "Feature",
  "properties": {
    "gn:admin1_code":"1.0",
    "gn:asciiname":"Leribe",
    "gn:country_code":"BW",
    "gn:dem":758,
    "gn:feature_class":"P",
    "gn:feature_code":"PPLL",
    "gn:name":"Leribe",
    "gn:population":0,
    "gn:timezone":"Africa/Gaborone",
    "iso:country":"BW",
    "name:ceb_x_preferred":[
        "Leribe"
    ],
    "name:deu_x_preferred":[
        "Leribe"
    ],
    "name:fin_x_preferred":[
        "Leribe"
    ],
    "name:swe_x_preferred":[
        "Leribe"
    ],
    "wof:name":"Leribe",
    "wof:placetype":"locality"
},
  "geometry": {"coordinates":[28.4206,-21.8839],"type":"Point"}
}