{
  "type": "Feature",
  "properties": {
    "gn:admin1_code":"1.0",
    "gn:asciiname":"Leboana",
    "gn:country_code":"BW",
    "gn:dem":885,
    "gn:feature_class":"P",
    "gn:feature_code":"PPLL",
    "gn:name":"Leboana",
    "gn:population":0,
    "gn:timezone":"Africa/Gaborone",
    "iso:country":"BW",
    "wof:name":"Leboana",
    "wof:placetype":"locality"
},
  "geometry": {"coordinates":[27.47873,-22.52041],"type":"Point"}
}