{
  "type": "Feature",
  "properties": {
    "gn:admin1_code":"1.0",
    "gn:asciiname":"Dinokwe",
    "gn:country_code":"BW",
    "gn:dem":949,
    "gn:feature_class":"P",
    "gn:feature_code":"PPLL",
    "gn:name":"Dinokwe",
    "gn:population":0,
    "gn:timezone":"Africa/Gaborone",
    "iso:country":"BW",
    "name:ceb_x_preferred":[
        "Dinokwe"
    ],
    "name:fra_x_preferred":[
        "Palla Road/Dinokwe"
    ],
    "name:ita_x_preferred":[
        "Palla Road/Dinokwe"
    ],
    "name:mlg_x_preferred":[
        "Palla Road/Dinokwe"
    ],
    "name:nld_x_preferred":[
        "Dinokwe"
    ],
    "name:pol_x_preferred":[
        "Palla Road/Dinokwe"
    ],
    "name:swa_x_preferred":[
        "Palla Road/Dinokwe"
    ],
    "name:swe_x_preferred":[
        "Dinokwe"
    ],
    "name:tsn_x_preferred":[
        "Dinokwe"
    ],
    "wof:name":"Dinokwe",
    "wof:placetype":"locality"
},
  "geometry": {"coordinates":[26.69698,-23.40921],"type":"Point"}
}