{
  "type": "Feature",
  "properties": {
    "gn:admin1_code":"6.0",
    "gn:asciiname":"Moetlo",
    "gn:country_code":"BW",
    "gn:dem":1079,
    "gn:feature_class":"P",
    "gn:feature_code":"PPLL",
    "gn:name":"Moetlo",
    "gn:population":0,
    "gn:timezone":"Africa/Gaborone",
    "iso:country":"BW",
    "wof:name":"Moetlo",
    "wof:placetype":"locality"
},
  "geometry": {"coordinates":[25.77615,-24.00409],"type":"Point"}
}