{
  "type": "Feature",
  "properties": {
    "gn:admin1_code":"1.0",
    "gn:asciiname":"Phatswane",
    "gn:country_code":"BW",
    "gn:dem":722,
    "gn:feature_class":"P",
    "gn:feature_code":"PPLL",
    "gn:name":"Phatswane",
    "gn:population":0,
    "gn:timezone":"Africa/Gaborone",
    "iso:country":"BW",
    "wof:name":"Phatswane",
    "wof:placetype":"locality"
},
  "geometry": {"coordinates":[28.52425,-21.89057],"type":"Point"}
}