{
  "type": "Feature",
  "properties": {
    "gn:admin1_code":"1.0",
    "gn:asciiname":"Kgaswe",
    "gn:country_code":"BW",
    "gn:dem":1008,
    "gn:feature_class":"P",
    "gn:feature_code":"PPLL",
    "gn:name":"Kgaswe",
    "gn:population":0,
    "gn:timezone":"Africa/Gaborone",
    "iso:country":"BW",
    "wof:name":"Kgaswe",
    "wof:placetype":"locality"
},
  "geometry": {"coordinates":[26.81302,-22.51858],"type":"Point"}
}