{
  "type": "Feature",
  "properties": {
    "iso:country":"BW",
    "name:ceb_x_preferred":[
        "Pilikwe"
    ],
    "name:eng_x_preferred":[
        "Pilikwe"
    ],
    "name:fra_x_preferred":[
        "Pilikwe"
    ],
    "name:ita_x_preferred":[
        "Pilikwe"
    ],
    "name:mlg_x_preferred":[
        "Pilikwe"
    ],
    "name:nld_x_preferred":[
        "Pilikwe"
    ],
    "name:pol_x_preferred":[
        "Pilikwe"
    ],
    "name:swa_x_preferred":[
        "Pilikwe"
    ],
    "name:swe_x_preferred":[
        "Pilikwe"
    ],
    "qs:gn_country":"BW",
    "qs:gn_fcode":"PPL",
    "qs:gn_pop":1375,
    "qs:name":"Pilikwe",
    "qs:name_adm0":"Botswana",
    "qs:name_adm1":"Central",
    "qs:photos":0,
    "qs:photos_1k":0,
    "qs:photos_9k":0,
    "qs:photos_9r":0,
    "qs:photos_all":0,
    "qs:photos_sr":0,
    "qs:placetype":"Town",
    "qs:pop_sr":"3",
    "qs:woe_adm0":23424755,
    "wof:name":"Pilikwe",
    "wof:placetype":"locality",
    "wof:population":1375
},
  "geometry": {"coordinates":[27.19376,-22.79904],"type":"Point"}
}