{
  "type": "Feature",
  "properties": {
    "gn:admin1_code":"10.0",
    "gn:asciiname":"Lwale",
    "gn:country_code":"BW",
    "gn:dem":1151,
    "gn:feature_class":"P",
    "gn:feature_code":"PPLL",
    "gn:name":"Lwale",
    "gn:population":0,
    "gn:timezone":"Africa/Gaborone",
    "iso:country":"BW",
    "wof:name":"Lwale",
    "wof:placetype":"locality"
},
  "geometry": {"coordinates":[25.35182,-24.70441],"type":"Point"}
}