{
  "type": "Feature",
  "properties": {
    "iso:country":"BW",
    "name:deu_x_preferred":[
        "Chobe"
    ],
    "name:ita_x_preferred":[
        "Chobe"
    ],
    "name:pol_x_preferred":[
        "Chobe"
    ],
    "name:por_x_preferred":[
        "Chobe"
    ],
    "name:rus_x_preferred":[
        "\u0427\u043e\u0431\u0435"
    ],
    "name:swe_x_preferred":[
        "Chobe"
    ],
    "qs:gn_pop":0,
    "qs:name":"Chobe",
    "qs:name_adm0":"Botswana",
    "qs:name_adm1":"North-West",
    "qs:photos":1459,
    "qs:photos_1k":296,
    "qs:photos_9k":6,
    "qs:photos_9r":7,
    "qs:photos_all":1459,
    "qs:photos_sr":12,
    "qs:placetype":"Town",
    "qs:pop_sr":"0",
    "qs:woe_adm0":23424755,
    "wd:wordcount":11,
    "wof:name":"Chobe",
    "wof:placetype":"locality"
},
  "geometry": {"coordinates":[25.158004,-17.792415],"type":"Point"}
}