{
  "type": "Feature",
  "properties": {
    "gn:admin1_code":"1.0",
    "gn:asciiname":"Leupane",
    "gn:country_code":"BW",
    "gn:dem":943,
    "gn:feature_class":"P",
    "gn:feature_code":"PPL",
    "gn:name":"Leupane",
    "gn:population":0,
    "gn:timezone":"Africa/Gaborone",
    "iso:country":"BW",
    "name:und_x_variant":[
        "Lupani"
    ],
    "wof:name":"Leupane",
    "wof:placetype":"locality"
},
  "geometry": {"coordinates":[27.031,-22.59154],"type":"Point"}
}