{
  "type": "Feature",
  "properties": {
    "gn:admin1_code":"6.0",
    "gn:asciiname":"Digwagwe Well",
    "gn:country_code":"BW",
    "gn:dem":1020,
    "gn:feature_class":"P",
    "gn:feature_code":"PPLL",
    "gn:name":"Digwagwe Well",
    "gn:population":0,
    "gn:timezone":"Africa/Gaborone",
    "iso:country":"BW",
    "wof:name":"Digwagwe Well",
    "wof:placetype":"locality"
},
  "geometry": {"coordinates":[25.79625,-24.21955],"type":"Point"}
}