{
  "type": "Feature",
  "properties": {
    "gn:admin1_code":"8.0",
    "gn:asciiname":"Gambule",
    "gn:country_code":"BW",
    "gn:dem":1243,
    "gn:feature_class":"P",
    "gn:feature_code":"PPL",
    "gn:name":"Gambule",
    "gn:population":0,
    "gn:timezone":"Africa/Gaborone",
    "iso:country":"BW",
    "wof:name":"Gambule",
    "wof:placetype":"locality"
},
  "geometry": {"coordinates":[27.3856,-20.51781],"type":"Point"}
}