{
  "type": "Feature",
  "properties": {
    "gn:admin1_code":"1.0",
    "gn:asciiname":"Mmai",
    "gn:country_code":"BW",
    "gn:dem":982,
    "gn:feature_class":"P",
    "gn:feature_code":"PPL",
    "gn:name":"Mmai",
    "gn:population":0,
    "gn:timezone":"Africa/Gaborone",
    "iso:country":"BW",
    "wof:name":"Mmai",
    "wof:placetype":"locality"
},
  "geometry": {"coordinates":[26.46407,-21.01281],"type":"Point"}
}