{
  "type": "Feature",
  "properties": {
    "gn:admin1_code":"5.0",
    "gn:asciiname":"Mmaubane",
    "gn:country_code":"BW",
    "gn:dem":935,
    "gn:feature_class":"P",
    "gn:feature_code":"PPLL",
    "gn:name":"Mmaubane",
    "gn:population":0,
    "gn:timezone":"Africa/Gaborone",
    "iso:country":"BW",
    "wof:name":"Mmaubane",
    "wof:placetype":"locality"
},
  "geometry": {"coordinates":[26.29716,-24.32936],"type":"Point"}
}