{
  "type": "Feature",
  "properties": {
    "gn:admin1_code":"12.0",
    "gn:asciiname":"Lesomo",
    "gn:country_code":"BW",
    "gn:dem":977,
    "gn:feature_class":"P",
    "gn:feature_code":"PPL",
    "gn:name":"Lesomo",
    "gn:population":0,
    "gn:timezone":"Africa/Gaborone",
    "iso:country":"BW",
    "wof:name":"Lesomo",
    "wof:placetype":"locality"
},
  "geometry": {"coordinates":[25.23409,-17.8958],"type":"Point"}
}