{
  "type": "Feature",
  "properties": {
    "gn:admin1_code":"0.0",
    "gn:asciiname":"Sehengos",
    "gn:cc2":"BW",
    "gn:country_code":"BW",
    "gn:dem":998,
    "gn:feature_class":"P",
    "gn:feature_code":"PPL",
    "gn:name":"Sehengos",
    "gn:population":0,
    "gn:timezone":"Africa/Gaborone",
    "iso:country":"BW",
    "name:und_x_variant":[
        "Sehengo",
        "Sehengos"
    ],
    "wof:name":"Sehengos",
    "wof:placetype":"locality"
},
  "geometry": {"coordinates":[21.78333,-18.26667],"type":"Point"}
}