{
  "type": "Feature",
  "properties": {
    "gn:admin1_code":"10.0",
    "gn:asciiname":"Metsae",
    "gn:country_code":"BW",
    "gn:dem":1194,
    "gn:feature_class":"P",
    "gn:feature_code":"PPLL",
    "gn:name":"Metsae",
    "gn:population":0,
    "gn:timezone":"Africa/Gaborone",
    "iso:country":"BW",
    "wof:name":"Metsae",
    "wof:placetype":"locality"
},
  "geometry": {"coordinates":[25.29674,-24.72034],"type":"Point"}
}