{
  "type": "Feature",
  "properties": {
    "gn:admin1_code":"1.0",
    "gn:asciiname":"Shate",
    "gn:country_code":"BW",
    "gn:dem":1093,
    "gn:feature_class":"P",
    "gn:feature_code":"PPL",
    "gn:name":"Shate",
    "gn:population":0,
    "gn:timezone":"Africa/Gaborone",
    "iso:country":"BW",
    "wof:name":"Shate",
    "wof:placetype":"locality"
},
  "geometry": {"coordinates":[26.8899,-21.24853],"type":"Point"}
}