{
  "type": "Feature",
  "properties": {
    "gn:admin1_code":"1.0",
    "gn:asciiname":"Matetsho",
    "gn:country_code":"BW",
    "gn:dem":1121,
    "gn:feature_class":"P",
    "gn:feature_code":"PPLL",
    "gn:name":"Matetsho",
    "gn:population":0,
    "gn:timezone":"Africa/Gaborone",
    "iso:country":"BW",
    "wof:name":"Matetsho",
    "wof:placetype":"locality"
},
  "geometry": {"coordinates":[26.47075,-23.10332],"type":"Point"}
}