{
  "type": "Feature",
  "properties": {
    "gn:admin1_code":"1.0",
    "gn:asciiname":"Ramogapele",
    "gn:country_code":"BW",
    "gn:dem":1031,
    "gn:feature_class":"P",
    "gn:feature_code":"PPLL",
    "gn:name":"Ramogapele",
    "gn:population":0,
    "gn:timezone":"Africa/Gaborone",
    "iso:country":"BW",
    "wof:name":"Ramogapele",
    "wof:placetype":"locality"
},
  "geometry": {"coordinates":[26.27206,-23.16238],"type":"Point"}
}