{
  "type": "Feature",
  "properties": {
    "gn:admin1_code":"1.0",
    "gn:asciiname":"Sinongope",
    "gn:country_code":"BW",
    "gn:dem":903,
    "gn:feature_class":"P",
    "gn:feature_code":"PPLL",
    "gn:name":"Sinongope",
    "gn:population":0,
    "gn:timezone":"Africa/Gaborone",
    "iso:country":"BW",
    "wof:name":"Sinongope",
    "wof:placetype":"locality"
},
  "geometry": {"coordinates":[27.34165,-22.57648],"type":"Point"}
}