{
  "type": "Feature",
  "properties": {
    "gn:admin1_code":"1.0",
    "gn:asciiname":"Mmabahuma",
    "gn:country_code":"BW",
    "gn:dem":1043,
    "gn:feature_class":"P",
    "gn:feature_code":"PPLL",
    "gn:name":"Mmabahuma",
    "gn:population":0,
    "gn:timezone":"Africa/Gaborone",
    "iso:country":"BW",
    "wof:name":"Mmabahuma",
    "wof:placetype":"locality"
},
  "geometry": {"coordinates":[26.59312000000001,-22.59199],"type":"Point"}
}