{
  "type": "Feature",
  "properties": {
    "gn:admin1_code":"10.0",
    "gn:asciiname":"Matlalo",
    "gn:country_code":"BW",
    "gn:dem":1190,
    "gn:feature_class":"P",
    "gn:feature_code":"PPLL",
    "gn:name":"Matlalo",
    "gn:population":0,
    "gn:timezone":"Africa/Gaborone",
    "iso:country":"BW",
    "wof:name":"Matlalo",
    "wof:placetype":"locality"
},
  "geometry": {"coordinates":[25.41973,-24.94073],"type":"Point"}
}