{
  "type": "Feature",
  "properties": {
    "gn:admin1_code":"10.0",
    "gn:asciiname":"Motswire",
    "gn:country_code":"BW",
    "gn:dem":1143,
    "gn:feature_class":"P",
    "gn:feature_code":"PPLL",
    "gn:name":"Motswire",
    "gn:population":0,
    "gn:timezone":"Africa/Gaborone",
    "iso:country":"BW",
    "wof:name":"Motswire",
    "wof:placetype":"locality"
},
  "geometry": {"coordinates":[25.53348,-24.94238],"type":"Point"}
}