{
  "type": "Feature",
  "properties": {
    "gn:admin1_code":"1.0",
    "gn:asciiname":"Piterolong",
    "gn:country_code":"BW",
    "gn:dem":936,
    "gn:feature_class":"P",
    "gn:feature_code":"PPLL",
    "gn:name":"Piterolong",
    "gn:population":0,
    "gn:timezone":"Africa/Gaborone",
    "iso:country":"BW",
    "wof:name":"Piterolong",
    "wof:placetype":"locality"
},
  "geometry": {"coordinates":[27.48381,-22.73523],"type":"Point"}
}