{
  "type": "Feature",
  "properties": {
    "gn:admin1_code":"0.0",
    "gn:asciiname":"Tsitle",
    "gn:country_code":"BW",
    "gn:dem":1119,
    "gn:feature_class":"P",
    "gn:feature_code":"PPL",
    "gn:name":"Tsitle",
    "gn:population":0,
    "gn:timezone":"Africa/Gaborone",
    "iso:country":"BW",
    "wof:name":"Tsitle",
    "wof:placetype":"locality"
},
  "geometry": {"coordinates":[25.71667,-23.23333],"type":"Point"}
}