{
  "type": "Feature",
  "properties": {
    "gn:admin1_code":"10.0",
    "gn:asciiname":"Ramoshengwane",
    "gn:country_code":"BW",
    "gn:dem":1128,
    "gn:feature_class":"P",
    "gn:feature_code":"PPLL",
    "gn:name":"Ramoshengwane",
    "gn:population":0,
    "gn:timezone":"Africa/Gaborone",
    "iso:country":"BW",
    "wof:name":"Ramoshengwane",
    "wof:placetype":"locality"
},
  "geometry": {"coordinates":[25.37748,-24.70149],"type":"Point"}
}