{
  "type": "Feature",
  "properties": {
    "gn:admin1_code":"6.0",
    "gn:asciiname":"Mogobewamusu",
    "gn:country_code":"BW",
    "gn:dem":1013,
    "gn:feature_class":"P",
    "gn:feature_code":"PPLL",
    "gn:name":"Mogobewamusu",
    "gn:population":0,
    "gn:timezone":"Africa/Gaborone",
    "iso:country":"BW",
    "wof:name":"Mogobewamusu",
    "wof:placetype":"locality"
},
  "geometry": {"coordinates":[25.87112,-24.1684],"type":"Point"}
}