{
  "type": "Feature",
  "properties": {
    "gn:admin1_code":"3.0",
    "gn:asciiname":"Karaka",
    "gn:country_code":"BW",
    "gn:dem":1159,
    "gn:feature_class":"P",
    "gn:feature_code":"PPL",
    "gn:name":"Karaka",
    "gn:population":0,
    "gn:timezone":"Africa/Gaborone",
    "iso:country":"BW",
    "name:ceb_x_preferred":[
        "Karaka"
    ],
    "name:deu_x_preferred":[
        "Karaka"
    ],
    "name:swe_x_preferred":[
        "Karaka"
    ],
    "wof:name":"Karaka",
    "wof:placetype":"locality"
},
  "geometry": {"coordinates":[21.38333,-21.78333],"type":"Point"}
}