{
  "type": "Feature",
  "properties": {
    "gn:admin1_code":"5.0",
    "gn:asciiname":"Lokala",
    "gn:country_code":"BW",
    "gn:dem":879,
    "gn:feature_class":"P",
    "gn:feature_code":"PPLL",
    "gn:name":"Lokala",
    "gn:population":0,
    "gn:timezone":"Africa/Gaborone",
    "iso:country":"BW",
    "wof:name":"Lokala",
    "wof:placetype":"locality"
},
  "geometry": {"coordinates":[26.69968,-23.95747],"type":"Point"}
}