{
  "type": "Feature",
  "properties": {
    "gn:admin1_code":"1.0",
    "gn:asciiname":"Kolojwana",
    "gn:country_code":"BW",
    "gn:dem":1068,
    "gn:feature_class":"P",
    "gn:feature_code":"PPL",
    "gn:name":"Kolojwana",
    "gn:population":0,
    "gn:timezone":"Africa/Gaborone",
    "iso:country":"BW",
    "wof:name":"Kolojwana",
    "wof:placetype":"locality"
},
  "geometry": {"coordinates":[27.36243,-22.25124],"type":"Point"}
}