{
  "type": "Feature",
  "properties": {
    "gn:admin1_code":"6.0",
    "gn:asciiname":"Ganthibedi",
    "gn:country_code":"BW",
    "gn:dem":1213,
    "gn:feature_class":"P",
    "gn:feature_code":"PPLL",
    "gn:name":"Ganthibedi",
    "gn:population":0,
    "gn:timezone":"Africa/Gaborone",
    "iso:country":"BW",
    "wof:name":"Ganthibedi",
    "wof:placetype":"locality"
},
  "geometry": {"coordinates":[25.31598,-24.31006],"type":"Point"}
}