{
  "type": "Feature",
  "properties": {
    "gn:admin1_code":"1.0",
    "gn:asciiname":"Karamechen",
    "gn:country_code":"BW",
    "gn:dem":938,
    "gn:feature_class":"P",
    "gn:feature_code":"PPL",
    "gn:name":"Karamechen",
    "gn:population":0,
    "gn:timezone":"Africa/Gaborone",
    "iso:country":"BW",
    "name:und_x_variant":[
        "Karamechen Stad",
        "Karamechen"
    ],
    "wof:name":"Karamechen",
    "wof:placetype":"locality"
},
  "geometry": {"coordinates":[27.75,-21.61667000000001],"type":"Point"}
}