{
  "type": "Feature",
  "properties": {
    "gn:admin1_code":"1.0",
    "gn:asciiname":"Kgolokwane",
    "gn:country_code":"BW",
    "gn:dem":735,
    "gn:feature_class":"P",
    "gn:feature_code":"PPLL",
    "gn:name":"Kgolokwane",
    "gn:population":0,
    "gn:timezone":"Africa/Gaborone",
    "iso:country":"BW",
    "wof:name":"Kgolokwane",
    "wof:placetype":"locality"
},
  "geometry": {"coordinates":[28.63591,-21.65928],"type":"Point"}
}