{
  "type": "Feature",
  "properties": {
    "gn:country":"BW",
    "gn:fcode":"PPL",
    "gn:pop":1043,
    "iso:country":"BW",
    "name:afr_x_preferred":[
        "D'Kar"
    ],
    "name:bul_x_preferred":[
        "\u0414\u0435\u043a\u0430\u0440"
    ],
    "name:ell_x_preferred":[
        "\u039d\u03c4\u03b5\u03ba\u03ac\u03c1"
    ],
    "name:eng_x_preferred":[
        "Dekar"
    ],
    "name:fra_x_preferred":[
        "Dekar"
    ],
    "name:ita_x_preferred":[
        "Dekar"
    ],
    "name:mlg_x_preferred":[
        "Dekar"
    ],
    "name:nld_x_preferred":[
        "Dekar"
    ],
    "name:pol_x_preferred":[
        "Dekar"
    ],
    "name:swa_x_preferred":[
        "Dekar"
    ],
    "name:swe_x_preferred":[
        "Dekar"
    ],
    "name:tsn_x_preferred":[
        "Dekar"
    ],
    "qs:name":"Dekar",
    "qs:photos_9r":0,
    "qs:photos_sr":0,
    "qs:pop_sr":"3",
    "wd:wordcount":231,
    "wof:name":"Dekar",
    "wof:placetype":"locality",
    "wof:population":1043
},
  "geometry": {"coordinates":[21.93333,-21.53333],"type":"Point"}
}