{
  "type": "Feature",
  "properties": {
    "gn:admin1_code":"1.0",
    "gn:asciiname":"Sofala",
    "gn:country_code":"BW",
    "gn:dem":892,
    "gn:feature_class":"P",
    "gn:feature_code":"PPL",
    "gn:name":"Sofala",
    "gn:population":0,
    "gn:timezone":"Africa/Gaborone",
    "iso:country":"BW",
    "name:ara_x_preferred":[
        "\u0633\u0641\u0627\u0644\u0629"
    ],
    "name:bel_x_preferred":[
        "\u0421\u0430\u0444\u0430\u043b\u0430"
    ],
    "name:cat_x_preferred":[
        "Sofala"
    ],
    "name:deu_x_preferred":[
        "Sofala"
    ],
    "name:fin_x_preferred":[
        "Sofala"
    ],
    "name:fra_x_preferred":[
        "Sofala"
    ],
    "name:heb_x_preferred":[
        "\u05e1\u05d5\u05e4\u05dc\u05d4"
    ],
    "name:hun_x_preferred":[
        "Sofala"
    ],
    "name:jpn_x_preferred":[
        "\u30bd\u30d5\u30a1\u30e9"
    ],
    "name:mal_x_preferred":[
        "\u0d38\u0d4b\u0d2b\u0d32"
    ],
    "name:nor_x_preferred":[
        "Sofala"
    ],
    "name:oci_x_preferred":[
        "Sofala"
    ],
    "name:por_x_preferred":[
        "Sofala"
    ],
    "name:rus_x_preferred":[
        "\u0421\u043e\u0444\u0430\u043b\u0430"
    ],
    "name:swa_x_preferred":[
        "Sofala"
    ],
    "name:ukr_x_preferred":[
        "\u0421\u043e\u0444\u0430\u043b\u0430"
    ],
    "wof:name":"Sofala",
    "wof:placetype":"locality"
},
  "geometry": {"coordinates":[27.46667,-23.03333],"type":"Point"}
}