{
  "type": "Feature",
  "properties": {
    "gn:admin1_code":"1.0",
    "gn:asciiname":"Sofala",
    "gn:country_code":"BW",
    "gn:dem":892,
    "gn:feature_class":"P",
    "gn:feature_code":"PPL",
    "gn:name":"Sofala",
    "gn:population":0,
    "gn:timezone":"Africa/Gaborone",
    "iso:country":"BW",
    "wof:name":"Sofala",
    "wof:placetype":"locality"
},
  "geometry": {"coordinates":[27.46667,-23.03333],"type":"Point"}
}