{
  "type": "Feature",
  "properties": {
    "gn:admin1_code":"8.0",
    "gn:asciiname":"Ramokgwebane",
    "gn:country_code":"BW",
    "gn:dem":1291,
    "gn:feature_class":"P",
    "gn:feature_code":"PPL",
    "gn:name":"Ramokgwebane",
    "gn:population":0,
    "gn:timezone":"Africa/Gaborone",
    "iso:country":"BW",
    "wof:name":"Ramokgwebane",
    "wof:placetype":"locality"
},
  "geometry": {"coordinates":[27.64157,-20.57663],"type":"Point"}
}