{
  "type": "Feature",
  "properties": {
    "gn:admin1_code":"1.0",
    "gn:asciiname":"Tloupye",
    "gn:country_code":"BW",
    "gn:dem":916,
    "gn:feature_class":"P",
    "gn:feature_code":"PPL",
    "gn:name":"Tloupye",
    "gn:population":0,
    "gn:timezone":"Africa/Gaborone",
    "iso:country":"BW",
    "name:und_x_variant":[
        "Tlopse"
    ],
    "wof:name":"Tloupye",
    "wof:placetype":"locality"
},
  "geometry": {"coordinates":[27.65,-22.35],"type":"Point"}
}