{
  "type": "Feature",
  "properties": {
    "gn:admin1_code":"0.0",
    "gn:asciiname":"Shaleshanto",
    "gn:country_code":"BW",
    "gn:dem":925,
    "gn:feature_class":"P",
    "gn:feature_code":"PPL",
    "gn:name":"Shaleshanto",
    "gn:population":0,
    "gn:timezone":"Africa/Gaborone",
    "iso:country":"BW",
    "wof:name":"Shaleshanto",
    "wof:placetype":"locality"
},
  "geometry": {"coordinates":[23.96667,-19.15],"type":"Point"}
}