{
  "type": "Feature",
  "properties": {
    "gn:admin1_code":"5.0",
    "gn:asciiname":"Mpepu",
    "gn:country_code":"BW",
    "gn:dem":950,
    "gn:feature_class":"P",
    "gn:feature_code":"PPLL",
    "gn:name":"Mpepu",
    "gn:population":0,
    "gn:timezone":"Africa/Gaborone",
    "iso:country":"BW",
    "wof:name":"Mpepu",
    "wof:placetype":"locality"
},
  "geometry": {"coordinates":[26.25251,-24.12282],"type":"Point"}
}