{
  "type": "Feature",
  "properties": {
    "gn:admin1_code":"6.0",
    "gn:asciiname":"Gakgatla",
    "gn:country_code":"BW",
    "gn:dem":1057,
    "gn:feature_class":"P",
    "gn:feature_code":"PPL",
    "gn:name":"Gakgatla",
    "gn:population":0,
    "gn:timezone":"Africa/Gaborone",
    "iso:country":"BW",
    "wof:name":"Gakgatla",
    "wof:placetype":"locality"
},
  "geometry": {"coordinates":[25.61745,-24.54303],"type":"Point"}
}