{
  "type": "Feature",
  "properties": {
    "gn:admin1_code":"6.0",
    "gn:asciiname":"Gakgatla",
    "gn:country_code":"BW",
    "gn:dem":1057,
    "gn:feature_class":"P",
    "gn:feature_code":"PPL",
    "gn:name":"Gakgatla",
    "gn:population":0,
    "gn:timezone":"Africa/Gaborone",
    "iso:country":"BW",
    "name:ceb_x_preferred":[
        "Gakgatla"
    ],
    "name:fra_x_preferred":[
        "Gakgatla"
    ],
    "name:ita_x_preferred":[
        "Gakgatla"
    ],
    "name:mlg_x_preferred":[
        "Gakgatla"
    ],
    "name:nld_x_preferred":[
        "Gakgatla"
    ],
    "name:pol_x_preferred":[
        "Gakgatla"
    ],
    "name:swa_x_preferred":[
        "Gakgatla"
    ],
    "name:swe_x_preferred":[
        "Gakgatla"
    ],
    "name:tsn_x_preferred":[
        "Gakgatla"
    ],
    "wof:name":"Gakgatla",
    "wof:placetype":"locality"
},
  "geometry": {"coordinates":[25.61745,-24.54303],"type":"Point"}
}