{
  "type": "Feature",
  "properties": {
    "gn:admin1_code":"1.0",
    "gn:asciiname":"Raisuwe",
    "gn:country_code":"BW",
    "gn:dem":829,
    "gn:feature_class":"P",
    "gn:feature_code":"PPLL",
    "gn:name":"Raisuwe",
    "gn:population":0,
    "gn:timezone":"Africa/Gaborone",
    "iso:country":"BW",
    "wof:name":"Raisuwe",
    "wof:placetype":"locality"
},
  "geometry": {"coordinates":[28.13856,-22.2203],"type":"Point"}
}