{
  "type": "Feature",
  "properties": {
    "gn:admin1_code":"8.0",
    "gn:asciiname":"Sikukwe",
    "gn:country_code":"BW",
    "gn:dem":1008,
    "gn:feature_class":"P",
    "gn:feature_code":"PPL",
    "gn:name":"Sikukwe",
    "gn:population":0,
    "gn:timezone":"Africa/Gaborone",
    "iso:country":"BW",
    "wof:name":"Sikukwe",
    "wof:placetype":"locality"
},
  "geometry": {"coordinates":[27.65202,-21.15469],"type":"Point"}
}