{
  "type": "Feature",
  "properties": {
    "gn:admin1_code":"6.0",
    "gn:asciiname":"Mantswabisi",
    "gn:country_code":"BW",
    "gn:dem":1193,
    "gn:feature_class":"P",
    "gn:feature_code":"PPL",
    "gn:name":"Mantswabisi",
    "gn:population":0,
    "gn:timezone":"Africa/Gaborone",
    "iso:country":"BW",
    "wof:name":"Mantswabisi",
    "wof:placetype":"locality"
},
  "geometry": {"coordinates":[25.30526,-24.20023],"type":"Point"}
}