{
  "type": "Feature",
  "properties": {
    "gn:admin1_code":"1.0",
    "gn:asciiname":"Selol'wane",
    "gn:country_code":"BW",
    "gn:dem":1085,
    "gn:feature_class":"P",
    "gn:feature_code":"PPLL",
    "gn:name":"Selol\u2019wane",
    "gn:population":0,
    "gn:timezone":"Africa/Gaborone",
    "iso:country":"BW",
    "wof:name":"Selol'wane",
    "wof:placetype":"locality"
},
  "geometry": {"coordinates":[27.01114,-20.48438],"type":"Point"}
}