{
  "type": "Feature",
  "properties": {
    "gn:admin1_code":"6.0",
    "gn:asciiname":"Kwanate",
    "gn:country_code":"BW",
    "gn:dem":1185,
    "gn:feature_class":"P",
    "gn:feature_code":"PPLL",
    "gn:name":"Kwanate",
    "gn:population":0,
    "gn:timezone":"Africa/Gaborone",
    "iso:country":"BW",
    "wof:name":"Kwanate",
    "wof:placetype":"locality"
},
  "geometry": {"coordinates":[25.41481,-24.08688],"type":"Point"}
}