{
  "type": "Feature",
  "properties": {
    "gn:admin1_code":"5.0",
    "gn:asciiname":"Masama",
    "gn:country_code":"BW",
    "gn:dem":951,
    "gn:feature_class":"P",
    "gn:feature_code":"PPLL",
    "gn:name":"Masama",
    "gn:population":0,
    "gn:timezone":"Africa/Gaborone",
    "iso:country":"BW",
    "name:run_x_preferred":[
        "Masama"
    ],
    "wof:name":"Masama",
    "wof:placetype":"locality"
},
  "geometry": {"coordinates":[26.38466,-23.84359],"type":"Point"}
}