{
  "type": "Feature",
  "properties": {
    "gn:admin1_code":"1.0",
    "gn:asciiname":"Borotsi",
    "gn:country_code":"BW",
    "gn:dem":933,
    "gn:feature_class":"P",
    "gn:feature_code":"PPLL",
    "gn:name":"Borotsi",
    "gn:population":0,
    "gn:timezone":"Africa/Gaborone",
    "iso:country":"BW",
    "wof:name":"Borotsi",
    "wof:placetype":"locality"
},
  "geometry": {"coordinates":[27.36116,-22.87251],"type":"Point"}
}