{
  "type": "Feature",
  "properties": {
    "gn:admin1_code":"1.0",
    "gn:asciiname":"Matshwane",
    "gn:country_code":"BW",
    "gn:dem":889,
    "gn:feature_class":"P",
    "gn:feature_code":"PPLL",
    "gn:name":"Matshwane",
    "gn:population":0,
    "gn:timezone":"Africa/Gaborone",
    "iso:country":"BW",
    "wof:name":"Matshwane",
    "wof:placetype":"locality"
},
  "geometry": {"coordinates":[28.0245,-21.68876],"type":"Point"}
}