{
  "type": "Feature",
  "properties": {
    "gn:admin1_code":"1.0",
    "gn:asciiname":"Maebele",
    "gn:country_code":"BW",
    "gn:dem":849,
    "gn:feature_class":"P",
    "gn:feature_code":"PPLL",
    "gn:name":"Maebele",
    "gn:population":0,
    "gn:timezone":"Africa/Gaborone",
    "iso:country":"BW",
    "wof:name":"Maebele",
    "wof:placetype":"locality"
},
  "geometry": {"coordinates":[28.2753,-21.73943],"type":"Point"}
}