{
  "type": "Feature",
  "properties": {
    "gn:admin1_code":"10.0",
    "gn:asciiname":"Kgome",
    "gn:country_code":"BW",
    "gn:dem":1185,
    "gn:feature_class":"P",
    "gn:feature_code":"PPL",
    "gn:name":"Kgome",
    "gn:population":0,
    "gn:timezone":"Africa/Gaborone",
    "iso:country":"BW",
    "wof:name":"Kgome",
    "wof:placetype":"locality"
},
  "geometry": {"coordinates":[24.65811,-24.58921],"type":"Point"}
}