{
  "type": "Feature",
  "properties": {
    "gn:admin1_code":"1.0",
    "gn:asciiname":"Seimatlwe",
    "gn:country_code":"BW",
    "gn:dem":971,
    "gn:feature_class":"P",
    "gn:feature_code":"PPLL",
    "gn:name":"Seimatlwe",
    "gn:population":0,
    "gn:timezone":"Africa/Gaborone",
    "iso:country":"BW",
    "wof:name":"Seimatlwe",
    "wof:placetype":"locality"
},
  "geometry": {"coordinates":[27.15796,-21.53424],"type":"Point"}
}