{
  "type": "Feature",
  "properties": {
    "gn:admin1_code":"1.0",
    "gn:asciiname":"Makolane",
    "gn:country_code":"BW",
    "gn:dem":1046,
    "gn:feature_class":"P",
    "gn:feature_code":"PPLL",
    "gn:name":"Makolane",
    "gn:population":0,
    "gn:timezone":"Africa/Gaborone",
    "iso:country":"BW",
    "wof:name":"Makolane",
    "wof:placetype":"locality"
},
  "geometry": {"coordinates":[26.19176,-23.13702],"type":"Point"}
}