{
  "type": "Feature",
  "properties": {
    "gn:admin1_code":"1.0",
    "gn:asciiname":"Kototse",
    "gn:country_code":"BW",
    "gn:dem":1014,
    "gn:feature_class":"P",
    "gn:feature_code":"PPLL",
    "gn:name":"Kototse",
    "gn:population":0,
    "gn:timezone":"Africa/Gaborone",
    "iso:country":"BW",
    "wof:name":"Kototse",
    "wof:placetype":"locality"
},
  "geometry": {"coordinates":[26.29358,-23.20685],"type":"Point"}
}