{
  "type": "Feature",
  "properties": {
    "gn:admin1_code":"10.0",
    "gn:asciiname":"Tlakhama",
    "gn:country_code":"BW",
    "gn:dem":1249,
    "gn:feature_class":"P",
    "gn:feature_code":"PPLL",
    "gn:name":"Tlakhama",
    "gn:population":0,
    "gn:timezone":"Africa/Gaborone",
    "iso:country":"BW",
    "wof:name":"Tlakhama",
    "wof:placetype":"locality"
},
  "geometry": {"coordinates":[25.42607000000001,-25.29743],"type":"Point"}
}