{
  "type": "Feature",
  "properties": {
    "gn:admin1_code":"1.0",
    "gn:asciiname":"Boswela",
    "gn:country_code":"BW",
    "gn:dem":723,
    "gn:feature_class":"P",
    "gn:feature_code":"PPLL",
    "gn:name":"Boswela",
    "gn:population":0,
    "gn:timezone":"Africa/Gaborone",
    "iso:country":"BW",
    "wof:name":"Boswela",
    "wof:placetype":"locality"
},
  "geometry": {"coordinates":[28.81672,-21.8425],"type":"Point"}
}