{
  "type": "Feature",
  "properties": {
    "gn:admin1_code":"1.0",
    "gn:asciiname":"Pupya",
    "gn:country_code":"BW",
    "gn:dem":911,
    "gn:feature_class":"P",
    "gn:feature_code":"PPL",
    "gn:name":"Pupya",
    "gn:population":0,
    "gn:timezone":"Africa/Gaborone",
    "iso:country":"BW",
    "wof:name":"Pupya",
    "wof:placetype":"locality"
},
  "geometry": {"coordinates":[27.49937000000001,-22.88871],"type":"Point"}
}