{
  "type": "Feature",
  "properties": {
    "gn:admin1_code":"1.0",
    "gn:asciiname":"Xoso",
    "gn:country_code":"BW",
    "gn:dem":1008,
    "gn:feature_class":"P",
    "gn:feature_code":"PPLL",
    "gn:name":"Xoso",
    "gn:population":0,
    "gn:timezone":"Africa/Gaborone",
    "iso:country":"BW",
    "wof:name":"Xoso",
    "wof:placetype":"locality"
},
  "geometry": {"coordinates":[26.87537,-23.11969],"type":"Point"}
}