{
  "type": "Feature",
  "properties": {
    "gn:country":"BW",
    "gn:fcode":"PPL",
    "gn:population":2377,
    "iso:country":"BW",
    "name:bul_x_preferred":[
        "\u0420\u0430\u0442\u0445\u043e\u043b\u043e"
    ],
    "name:ceb_x_preferred":[
        "Ratholo"
    ],
    "name:eng_x_preferred":[
        "Ratholo"
    ],
    "name:fra_x_preferred":[
        "Ratholo"
    ],
    "name:ita_x_preferred":[
        "Ratholo"
    ],
    "name:mlg_x_preferred":[
        "Ratholo"
    ],
    "name:nld_x_preferred":[
        "Ratholo"
    ],
    "name:pol_x_preferred":[
        "Ratholo"
    ],
    "name:swa_x_preferred":[
        "Ratholo"
    ],
    "name:swe_x_preferred":[
        "Ratholo"
    ],
    "name:und_x_variant":[
        "Ratolo"
    ],
    "qs:name":"Ratholo",
    "qs:photos_9r":0,
    "qs:photos_sr":0,
    "qs:pop_sr":"4",
    "wof:name":"Ratholo",
    "wof:placetype":"locality",
    "wof:population":2377
},
  "geometry": {"coordinates":[27.57199,-22.72454],"type":"Point"}
}