{
  "type": "Feature",
  "properties": {
    "gn:admin1_code":"0.0",
    "gn:asciiname":"Rakops",
    "gn:country_code":"BW",
    "gn:dem":915,
    "gn:feature_class":"P",
    "gn:feature_code":"PPL",
    "gn:name":"Rakops",
    "gn:population":0,
    "gn:timezone":"Africa/Gaborone",
    "iso:country":"BW",
    "wof:name":"Rakops",
    "wof:placetype":"locality"
},
  "geometry": {"coordinates":[24.41667,-21.05],"type":"Point"}
}