{
  "type": "Feature",
  "properties": {
    "gn:admin1_code":"0.0",
    "gn:asciiname":"Rakops",
    "gn:country_code":"BW",
    "gn:dem":915,
    "gn:feature_class":"P",
    "gn:feature_code":"PPL",
    "gn:name":"Rakops",
    "gn:population":0,
    "gn:timezone":"Africa/Gaborone",
    "iso:country":"BW",
    "name:fas_x_preferred":[
        "\u0631\u0627\u06a9\u0648\u067e\u0633"
    ],
    "name:fra_x_preferred":[
        "Tsienyane/Rakops"
    ],
    "name:ita_x_preferred":[
        "Tsienyane/Rakops"
    ],
    "name:mlg_x_preferred":[
        "Tsienyane/Rakops"
    ],
    "name:nld_x_preferred":[
        "Tsienyane"
    ],
    "name:pol_x_preferred":[
        "Tsienyane"
    ],
    "name:spa_x_preferred":[
        "Tsienyane"
    ],
    "name:swa_x_preferred":[
        "Tsienyane/Rakops"
    ],
    "name:swe_x_preferred":[
        "Rakops"
    ],
    "name:tsn_x_preferred":[
        "Rakops"
    ],
    "name:zho_x_preferred":[
        "\u62c9\u79d1\u666e\u65af"
    ],
    "wof:name":"Rakops",
    "wof:placetype":"locality"
},
  "geometry": {"coordinates":[24.41667,-21.05],"type":"Point"}
}